Workbook

Sheet Supuestos
A1: Supuestos del modelo (millones de US$, salvo indicación)
A2: Convención: azul = dato o supuesto escrito a mano; negro = fórmula; verde = vínculo a otra hoja; fondo amarillo = selector o supuesto clave que se puede cambiar.
A4: 1. Mercado, deuda e impuestos
C5: Valor | I5: Fuente / tipo
A6: Tasa de impuestos | C6: 0.4 | I6: Caso, Anexo 1 (40% en todos los años proyectados).
A7: Costo de la deuda (Kd), BBB+ | C7: 0.055 | I7: Caso, p. 8: 'tasa de interés de aproximadamente 5,50%'.
A8: Diferencial sobre el bono del Tesoro a 10 años | C8: 0.0125 | I8: Caso, p. 8: '125 pb sobre el rendimiento actual del Tesoro a 10 años'.
A9: Tasa libre de riesgo (Tesoro a 10 años) = Kd − diferencial | C9: =C7-C8 -> 0.0425 | I9: Derivada del caso (5,50% − 1,25%). El caso no da el plazo de 20 o 30 años.
A10: Prima de riesgo de mercado (PRM) | C10: 0.05 | I10: Caso, p. 8: recomendación de Bianco (R&R). No dice período ni si es promedio aritmético o geométrico.
A11: Cobertura EBITDA / intereses para dimensionar la deuda | C11: 5 | I11: Caso, p. 2 y p. 8 (≥ 5,0x sobre EBITDA 2007).
A12: Deuda / valor máximo admitido | C12: 0.5 | I12: Caso, p. 2 y p. 8 (45%-50%).
A13: Plazo de amortización de la deuda (meses) | C13: 120 | I13: Caso, p. 8 y Anexo 6.
A14: Mes del pago bullet (refinanciación) | C14: 60 | I14: Caso, p. 8: pago bullet al final del año 5.
A15: Múltiplo P/U histórico de la industria | C15: 19.095 | I15: Caso, nota 3.
A16: Costo de salir a bolsa (% del patrimonio), tope razonable del descuento | C16: 0.1 | I16: Caso, nota 6.
A17: Descuento por iliquidez, Anexo 8 (empresa rentable, ingresos US$1.000 MM) | C17: 0.157 | I17: Lectura aproximada de un gráfico (imagen); el valor exacto no está en el caso.
A18: Descuento por iliquidez, regla práctica (20%-30%), punto medio | C18: 0.25 | I18: Caso, p. 8.
A19: Descuento por iliquidez, investigación académica | C19: 0.35 | I19: Caso, p. 8 y nota 5 (Moroney 35%; Silber 33,75%).
A21: 2. Selectores de decisiones metodológicas (cambiar el número para ver el efecto)
A22: Beta desapalancada: 1 = Hamada (βd = 0); 2 = Harris-Pringle (βd = 0); 3 = Harris-Pringle con βd implícita | C22: 3 | I22: Elección propia: la deuda BBB+ paga 125 pb sobre el Tesoro, así que su beta no es cero (ver hoja Costo_Capital).
A23: Estructura objetivo D/V: 1 = promedio comparables; 2 = mediana comparables; 3 = máximo de R&R (50%) | C23: 1 | I23: Caso, p. 8: la deuda se paga hasta niveles de la industria; nota del Anexo 7: promedio de 3 años.
A24: Crecimiento a perpetuidad: 1 = fundamental (ROIC × tasa de reinversión 2012); 2 = manual | C24: 1 | I24: Caso, p. 8 y notas 7 y 8: g depende del retorno sobre el capital y de la tasa de reinversión.
A25: Crecimiento manual (solo si el selector anterior = 2) | C25: 0.03 | I25: Supuesto propio para sensibilidad; no sale del caso.
A26: Múltiplo terminal VE/EBITDA: 1 = promedio comparables; 2 = mediana | C26: 2 | I26: Elección propia: la mediana es menos sensible a los extremos (2,6x a 19,1x).
A27: Valor de afiliadas e interés minoritario: 1 = P/U de la industria; 2 = valor en libros | C27: 1 | I27: Caso, p. 6 y nota 3 (Jennifer propone múltiplos de mercado).
A28: Margen de las sinergias de ingresos: 1 = margen EBITDA proyectado de ATC; 2 = margen sin SG&A ni equipos | C28: 1 | I28: El caso (Tabla 5) solo da ingresos, no la utilidad bruta que menciona el texto. Supuesto propio.
A29: Descuento por iliquidez aplicado al patrimonio | C29: 0 | I29: Elección propia (ver informe): comprador estratégico del 100%, empresa grande y rentable con opción de salir a bolsa.
A30: Porcentaje de sinergias que se realiza | C30: 1 | I30: Escenario base del caso (Tablas 4 y 5).
A31: Parte de las sinergias de backhaul que se cede al vendedor en el precio objetivo | C31: 0.5 | I31: Supuesto propio de negociación (reparto en partes iguales de la sinergia más cierta).
A32: Variación de g para el análisis tornado (± pp) | C32: 0.005 | I32: Supuesto propio para sensibilidad.
A34: 3. Supuestos operativos 2008-2012 (Anexo 1)
A35: Año | D35: 2008 | E35: 2009 | F35: 2010 | G35: 2011 | H35: 2012
A36: Crecimiento de ingresos por servicios | D36: 0.14 | E36: 0.14 | F36: 0.125 | G36: 0.1 | H36: 0.07 | I36: Caso, Anexo 1.
A37: Costos de operación del sistema / ingresos por servicios | D37: 0.2 | E37: 0.2 | F37: 0.2 | G37: 0.2 | H37: 0.2 | I37: Caso, Anexo 1.
A38: Costo de equipos vendidos / ingresos por equipos | D38: 2.4 | E38: 2.4 | F38: 2.4 | G38: 2.4 | H38: 2.4 | I38: Caso, Anexo 1 (240%: los equipos se subsidian).
A39: SG&A / ingresos totales | D39: 0.4 | E39: 0.4 | F39: 0.4 | G39: 0.4 | H39: 0.4 | I39: Caso, Anexo 1.
A40: Depreciación y amortización | D40: 705.22932 | E40: 803.96142 | F40: 867.43875 | G40: 922.37654 | H40: 952.91038 | I40: Caso, Anexo 1 (valores absolutos).
A41: Capex / ingresos totales | D41: 0.14 | E41: 0.14 | F41: 0.15 | G41: 0.1525 | H41: 0.155 | I41: Caso, Anexo 1 (incluye licencias y listas de clientes).
A42: D&A / ingresos totales (implícito en el Anexo 1) | D42: =D40/Proyeccion!D8 -> 0.15640123 | E42: =E40/Proyeccion!E8 -> 0.15640123 | F42: =F40/Proyeccion!F8 -> 0.15 | G42: =G40/Proyeccion!G8 -> 0.145 | H42: =H40/Proyeccion!H8 -> 0.14 | I42: Derivado: D&A del Anexo 1 / ingresos del escenario base. En los escenarios la D&A se mueve con los ingresos.
A44: Razones de capital de trabajo (promedio 2005-2007, año de 360 días)
A45: Ingresos por equipos / ingresos por servicios | C45: =Historicos!$E$194 -> 0.075047299 | I45: Promedio histórico; coincide con el 7,5% del Anexo 1.
A46: Días de cartera (sobre ingresos totales) | C46: =Historicos!$E$195 -> 41.667319 | I46: Promedio histórico; coincide con 41,67 del Anexo 1.
A47: Días de inventario (sobre ingresos por equipos) | C47: =Historicos!$E$196 -> 154.36021 | I47: Promedio histórico; coincide con 154,36 del Anexo 1. Se calcula sobre ingresos de equipos, no sobre su costo.
A48: Gastos prepagados / costos operativos en efectivo | C48: =Historicos!$E$197 -> 0.013806751 | I48: Promedio histórico = 1,38% del Anexo 1. El anexo no dice la base; solo cuadra con costos operativos en efectivo.
A49: Días de proveedores (sobre costos operativos en efectivo) | C49: =Historicos!$E$198 -> 35.53649 | I49: Promedio histórico; coincide con 35,54.
A50: Días de ingresos diferidos (sobre ingresos por servicios) | C50: =Historicos!$E$199 -> 14.012137 | I50: Promedio histórico = 14,01. La nota del Anexo 1 dice 'costos operativos en efectivo', pero solo cuadra con ingresos por servicios.
A51: Días de pasivos acumulados (sobre costos operativos en efectivo) | C51: =Historicos!$E$200 -> 6.8450583 | I51: Promedio histórico; coincide con 6,85.
A53: 4. Sinergias (Tablas 4 y 5)
A54: Año | D54: 2008 | E54: 2009 | F54: 2010 | G54: 2011 | H54: 2012
A55: Costo de backhaul / costos de operación del sistema | D55: 0.2 | E55: 0.2 | F55: 0.2 | G55: 0.2 | H55: 0.2 | I55: Caso, p. 6 y Tabla 4.
A56: Reducción del costo de backhaul | D56: 0 | E56: 0.07 | F56: 0.12 | G56: 0.222 | H56: 0.3 | I56: Caso, Tabla 4.
A57: Suscriptores empresariales promedio (millones) | D57: 0.3 | E57: 0.5 | F57: 0.7 | G57: 1 | H57: 1.2 | I57: Caso, Tabla 5.
A58: Minutos promedio mensuales por suscriptor | D58: 859 | E58: 885 | F58: 911 | G58: 939 | H58: 967 | I58: Caso, Tabla 5.
A59: Ingreso por minuto, clientes empresariales (US$) | D59: 0.0506 | E59: 0.0506 | F59: 0.0506 | G59: 0.0506 | H59: 0.0506 | I59: Caso, Tabla 5.
A61: 5. Escenarios de riesgo (supuestos propios, motivados por el caso)
C62: Base | D62: Precios | E62: Adquisición | F62: Combinado
A63: Ajuste al crecimiento de ingresos por servicios (pp por año) | C63: 0 | D63: -0.03 | E63: 0 | F63: -0.03 | I63: El ingreso por minuto cayó 11% en 2007 (Anexo 3). Supuesto propio: −3 pp de crecimiento cada año.
A64: Ajuste a SG&A / ingresos totales (pp) | C64: 0 | D64: 0 | E64: 0.02 | F64: 0.02 | I64: El costo por cliente nuevo subió de US$385 a US$487 en 2007 (Anexo 3). Supuesto propio: +2 pp de SG&A.
A65: Ajuste a capex / ingresos (pp) | C65: 0 | D65: 0 | E65: 0 | F65: 0 | I65: Disponible para otros escenarios; en cero.

Sheet Historicos
A1: Datos históricos 2005-2007, controles de consistencia e indicadores (millones de US$)
A3: A. Estado de resultados (Anexo 4)
C4: 2005 | D4: 2006 | E4: 2007
A5: Ingresos por servicios | C5: 2827.022 | D5: 3214.41 | E5: 3679.237
A6: Ingresos por equipos | C6: 203.743 | D6: 258.745 | E6: 267.027
A7: Ingresos totales | C7: =C5+C6 -> 3030.765 | D7: =D5+D6 -> 3473.155 | E7: =E5+E6 -> 3946.264
A8: Costos de operación del sistema | C8: 604.093 | D8: 639.683 | E8: 717.075
A9: Costo de equipos vendidos | C9: 511.939 | D9: 568.903 | E9: 640.225
A10: Gastos de ventas, generales y de administración (SG&A) | C10: 1217.709 | D10: 1399.561 | E10: 1555.639
A11: EBITDA | C11: =C7-C8-C9-C10 -> 697.024 | D11: =D7-D8-D9-D10 -> 865.008 | E11: =E7-E8-E9-E10 -> 1033.325
A12: Depreciación y amortización | C12: 490.093 | D12: 555.525 | E12: 582.269
A13: EBIT (utilidad operativa) | C13: =C11-C12 -> 206.931 | D13: =D11-D12 -> 309.483 | E13: =E11-E12 -> 451.056
A14: Gasto de intereses | C14: 84.867 | D14: 93.674 | E14: 84.679
A15: Participación en utilidades de afiliadas | C15: 66.719 | D15: 93.119 | E15: 90.033
A16: Ganancias (pérdidas) en inversiones | C16: 18.063 | D16: 50.84 | E16: 83.13
A17: Otros ingresos | C17: 54.501 | D17: -46.63 | E17: 6.961
A18: Utilidad antes de impuestos | C18: =C13-C14+C15+C16+C17 -> 261.347 | D18: =D13-D14+D15+D16+D17 -> 313.138 | E18: =E13-E14+E15+E16+E17 -> 546.501
A19: Impuestos | C19: 95.856 | D19: 120.604 | E19: 216.711
A20: Utilidad antes de interés minoritario | C20: =C18-C19 -> 165.491 | D20: =D18-D19 -> 192.534 | E20: =E18-E19 -> 329.79
A21: Interés minoritario | C21: 10.54 | D21: 13.044 | E21: 15.056
A22: Utilidad neta | C22: =C20-C21 -> 154.951 | D22: =D20-D21 -> 179.49 | E22: =E20-E21 -> 314.734
A24: Control: subtotales publicados en el Anexo 4 (PDF) | G24: Diferencia máx.
A25: Ingresos totales publicado | C25: 3030.8 | D25: 3473.2 | E25: 3946.3 | G25: =MAX(ABS(C25-C7),ABS(D25-D7),ABS(E25-E7)) -> 0.045 | H25: =IF(G25<0.06,"Cuadra (redondeo)","NO CUADRA") -> Cuadra (redondeo)
A26: EBITDA publicado | C26: 697 | D26: 865 | E26: 1033.3 | G26: =MAX(ABS(C26-C11),ABS(D26-D11),ABS(E26-E11)) -> 0.025 | H26: =IF(G26<0.06,"Cuadra (redondeo)","NO CUADRA") -> Cuadra (redondeo)
A27: EBIT (utilidad operativa) publicado | C27: 206.9 | D27: 309.5 | E27: 451.1 | G27: =MAX(ABS(C27-C13),ABS(D27-D13),ABS(E27-E13)) -> 0.044 | H27: =IF(G27<0.06,"Cuadra (redondeo)","NO CUADRA") -> Cuadra (redondeo)
A28: Utilidad antes de impuestos publicado | C28: 261.3 | D28: 313.1 | E28: 546.5 | G28: =MAX(ABS(C28-C18),ABS(D28-D18),ABS(E28-E18)) -> 0.047 | H28: =IF(G28<0.06,"Cuadra (redondeo)","NO CUADRA") -> Cuadra (redondeo)
A29: Utilidad antes de interés minoritario publicado | C29: 165.5 | D29: 192.5 | E29: 329.8 | G29: =MAX(ABS(C29-C20),ABS(D29-D20),ABS(E29-E20)) -> 0.034 | H29: =IF(G29<0.06,"Cuadra (redondeo)","NO CUADRA") -> Cuadra (redondeo)
A30: Utilidad neta publicado | C30: 155 | D30: 179.5 | E30: 314.7 | G30: =MAX(ABS(C30-C22),ABS(D30-D22),ABS(E30-E22)) -> 0.049 | H30: =IF(G30<0.06,"Cuadra (redondeo)","NO CUADRA") -> Cuadra (redondeo)
A31: Diferencia máxima de todos los subtotales del estado de resultados | G31: =MAX(G25:G30) -> 0.049
A33: B. Balance general (Anexo 5)
C34: 2005 | D34: 2006 | E34: 2007
A35: Caja y equivalentes | C35: 29.003 | D35: 32.912 | E35: 204.533
A36: Valores negociables | C36: 0 | D36: 249.039 | E36: 16.352
A37: Cuentas por cobrar | C37: 362.359 | D37: 407.438 | E37: 435.497
A38: Inventario | C38: 92.748 | D38: 117.189 | E38: 100.99
A39: Gastos prepagados | C39: 32.068 | D39: 34.955 | E39: 41.588
A40: Impuestos diferidos (activo corriente) | C40: 8.218 | D40: 0 | E40: 18.566
A41: Otros activos corrientes | C41: 15.489 | D41: 13.385 | E41: 16.227
A42: Total activos corrientes | C42: =SUM(C35:C41) -> 539.885 | D42: =SUM(D35:D41) -> 854.918 | E42: =SUM(E35:E41) -> 833.753
A43: Propiedad, planta y equipo | C43: 2553.029 | D43: 2628.848 | E43: 2595.096
A44: Licencias | C44: 1362.263 | D44: 1494.327 | E44: 1482.446
A45: Listas de clientes | C45: 47.649 | D45: 26.196 | E45: 15.375
A46: Títulos de renta variable negociables | C46: 225.387 | D46: 4.873 | E46: 0
A47: Inversiones en entidades afiliadas | C47: 172.093 | D47: 150.325 | E47: 157.693
A48: Nota por cobrar de largo plazo | C48: 4.707 | D48: 4.541 | E48: 4.422
A49: Plusvalía (goodwill) | C49: 481.235 | D49: 485.452 | E49: 491.316
A50: Otros activos de largo plazo | C50: 29.985 | D50: 31.136 | E50: 31.773
A51: Total activos | C51: =C42+SUM(C43:C50) -> 5416.233 | D51: =D42+SUM(D43:D50) -> 5680.616 | E51: =E42+SUM(E43:E50) -> 5611.874
A52: Cuentas por pagar | C52: 254.116 | D52: 254.871 | E52: 260.791
A53: Ingresos diferidos y depósitos | C53: 111.407 | D53: 123.344 | E53: 143.445
A54: Pasivos acumulados | C54: 42.865 | D54: 47.842 | E54: 59.224
A55: Impuestos por pagar | C55: 36.748 | D55: 26.913 | E55: 43.105
A56: Impuestos diferidos (pasivo corriente) | C56: 0 | D56: 26.326 | E56: 0
A57: Pagaré (deuda de corto plazo) | C57: 135 | D57: 35 | E57: 0
A58: Contrato a plazo (corriente) | C58: 0 | D58: 159.856 | E58: 0
A59: Pasivo por derivados (corriente) | C59: 0 | D59: 88.84 | E59: 0
A60: Otros pasivos corrientes | C60: 82.585 | D60: 93.718 | E60: 97.678
A61: Total pasivos corrientes | C61: =SUM(C52:C60) -> 662.721 | D61: =SUM(D52:D60) -> 856.71 | E61: =SUM(E52:E60) -> 604.243
A62: Deuda de largo plazo | C62: 1001.385 | D62: 1001.839 | E62: 1002.293
A63: Contratos a plazo (largo plazo) | C63: 159.856 | D63: 0 | E63: 0
A64: Pasivo por derivados (largo plazo) | C64: 25.818 | D64: 0 | E64: 0
A65: Pasivo por impuestos diferidos | C65: 647.086 | D65: 601.535 | E65: 554.412
A66: Obligación por retiro de activos | C66: 90.224 | D66: 127.639 | E66: 126.844
A67: Otros pasivos diferidos | C67: 46.234 | D67: 62.914 | E67: 84.53
A68: Interés minoritario | C68: 41.871 | D68: 36.7 | E68: 43.396
A69: Capital: componente 1 (oculto en la fórmula del Excel del caso) | C69: 55.046 | D69: 55.046 | E69: 55.046
A70: Capital: componente 2 (oculto en la fórmula) | C70: 33.006 | D70: 33.006 | E70: 33.006
A71: Capital: componente 3, capital pagado adicional (oculto en la fórmula) | C71: 1286.964 | D71: 1290.829 | E71: 1316.042
A72: Acciones comunes y capital pagado (total publicado) | C72: =C69+C70+C71 -> 1375.016 | D72: =D69+D70+D71 -> 1378.881 | E72: =E69+E70+E71 -> 1404.094
A73: Utilidades retenidas: componente 1 (oculto en la fórmula) | C73: 1368.988 | D73: 1548.478 | E73: 1823.022
A74: Utilidades retenidas: componente 2 (oculto) | C74: 44.122 | D74: 80.382 | E74: 10.134
A75: Utilidades retenidas: componente 3 (oculto, se resta) | C75: 47.088 | D75: 14.462 | E75: 41.094
A76: Utilidades retenidas (total publicado) | C76: =C73+C74-C75 -> 1366.022 | D76: =D73+D74-D75 -> 1614.398 | E76: =E73+E74-E75 -> 1792.062
A77: Total pasivos y patrimonio | C77: =C61+SUM(C62:C68)+C72+C76 -> 5416.233 | D77: =D61+SUM(D62:D68)+D72+D76 -> 5680.616 | E77: =E61+SUM(E62:E68)+E72+E76 -> 5611.874
A79: Control: activos − pasivos y patrimonio | C79: =C51-C77 -> 0 | D79: =D51-D77 -> 0 | E79: =E51-E77 -> 0 | G79: =MAX(ABS(C79),ABS(D79),ABS(E79)) -> 0 | H79: =IF(G79<0.001,"El balance cuadra","NO CUADRA") -> El balance cuadra
A80: Control: totales publicados en el Anexo 5 (PDF) | G80: Diferencia máx.
A81: Total activos corrientes – publicado | C81: 539.9 | D81: 854.9 | E81: 833.8 | G81: =MAX(ABS(C81-C42),ABS(D81-D42),ABS(E81-E42)) -> 0.047 | H81: =IF(G81<0.06,"Cuadra (redondeo)","NO CUADRA") -> Cuadra (redondeo)
A82: Total activos – publicado | C82: 5416.2 | D82: 5680.6 | E82: 5611.9 | G82: =MAX(ABS(C82-C51),ABS(D82-D51),ABS(E82-E51)) -> 0.033 | H82: =IF(G82<0.06,"Cuadra (redondeo)","NO CUADRA") -> Cuadra (redondeo)
A83: Total pasivos corrientes – publicado | C83: 662.7 | D83: 856.7 | E83: 604.2 | G83: =MAX(ABS(C83-C61),ABS(D83-D61),ABS(E83-E61)) -> 0.043 | H83: =IF(G83<0.06,"Cuadra (redondeo)","NO CUADRA") -> Cuadra (redondeo)
A84: Acciones comunes y capital pagado (total publicado) – publicado | C84: 1375 | D84: 1378.9 | E84: 1404.1 | G84: =MAX(ABS(C84-C72),ABS(D84-D72),ABS(E84-E72)) -> 0.019 | H84: =IF(G84<0.06,"Cuadra (redondeo)","NO CUADRA") -> Cuadra (redondeo)
A85: Utilidades retenidas (total publicado) – publicado | C85: 1366 | D85: 1614.4 | E85: 1792.1 | G85: =MAX(ABS(C85-C76),ABS(D85-D76),ABS(E85-E76)) -> 0.038 | H85: =IF(G85<0.06,"Cuadra (redondeo)","NO CUADRA") -> Cuadra (redondeo)
A86: Total pasivos y patrimonio – publicado | C86: 5416.2 | D86: 5680.6 | E86: 5611.9 | G86: =MAX(ABS(C86-C77),ABS(D86-D77),ABS(E86-E77)) -> 0.033 | H86: =IF(G86<0.06,"Cuadra (redondeo)","NO CUADRA") -> Cuadra (redondeo)
A87: Diferencia máxima de los totales del balance | G87: =MAX(G81:G86) -> 0.047
A89: C. Conciliaciones
A90: Patrimonio contable (capital + utilidades retenidas) | C90: =C72+C76 -> 2741.038 | D90: =D72+D76 -> 2993.279 | E90: =E72+E76 -> 3196.156
A91: Variación de utilidades retenidas (componente 1) | D91: =D73-C73 -> 179.49 | E91: =E73-D73 -> 274.544
A92: Menos: utilidad neta del año | D92: =-D22 -> -179.49 | E92: =-E22 -> -314.734
A93: Diferencia = dividendos u otros cargos implícitos | D93: =D91+D92 -> 0 | E93: =E91+E92 -> -40.19 | H93: 2006 cuadra; en 2007 faltan ~40 (dividendos u otro ajuste no informado).
A94: Variación de utilidades retenidas publicadas − utilidad neta | D94: =D76-C76-D22 -> 68.886 | E94: =E76-D76-E22 -> -137.07 | H94: La línea publicada mezcla utilidades retenidas con otros componentes (probablemente ORI).
A96: Activo fijo neto (PP&E + licencias + listas de clientes) | C96: =C43+C44+C45 -> 3962.941 | D96: =D43+D44+D45 -> 4149.371 | E96: =E43+E44+E45 -> 4092.917
A97: Capex implícito = Δ activo fijo neto + D&A | D97: =D96-C96+D12 -> 741.955 | E97: =E96-D96+E12 -> 525.815 | H97: El caso no publica el capex histórico; se deduce del balance (supone sin ventas ni deterioros).
A98: Capex implícito / ingresos totales | D98: =D97/D7 -> 0.21362565 | E98: =E97/E7 -> 0.13324375
A100: D. Indicadores (módulo 2)
C101: 2005 | D101: 2006 | E101: 2007 | G101: Comparables
A102: Crecimiento de ingresos totales | D102: =D7/C7-1 -> 0.14596645 | E102: =E7/D7-1 -> 0.1362188
A103: Crecimiento de ingresos por servicios | D103: =D5/C5-1 -> 0.13703042 | E103: =E5/D5-1 -> 0.14460725
A104: Margen EBITDA | C104: =C11/C7 -> 0.22998286 | D104: =D11/D7 -> 0.2490554 | E104: =E11/E7 -> 0.26184893 | G104: =Comparables!M14 -> 0.316
A105: Margen EBIT | C105: =C13/C7 -> 0.068276821 | D105: =D13/D7 -> 0.089107166 | E105: =E13/E7 -> 0.1142995 | G105: =Comparables!L14 -> 0.156
A106: Margen neto | C106: =C22/C7 -> 0.051126036 | D106: =D22/D7 -> 0.051679237 | E106: =E22/E7 -> 0.079754928 | G106: =Comparables!N14 -> 0.066
A107: Margen de equipos (ingresos − costo) / ingresos por equipos | C107: =(C6-C9)/C6 -> -1.5126704 | D107: =(D6-D9)/D6 -> -1.1987014 | E107: =(E6-E9)/E6 -> -1.397604
...

Sheet Comparables
A1: Comparables inalámbricos (Anexo 7) y Tabla 3
A2: Unidades del Anexo 7 rotuladas como miles de US$; por magnitud parecen millones. Las razones no dependen de la unidad.
A4: Empresa | B4: Patrimonio de mercado | C4: Deuda neta | D4: D/V publicado | E4: D/P publicado | F4: Beta patrimonio | G4: Ingresos | H4: EBIT | I4: EBITDA | J4: Utilidad neta | K4: D/V calculado | L4: Margen EBIT | M4: Margen EBITDA | N4: Margen neto | O4: Valor empresa (VE) | P4: VE/EBITDA | Q4: VE/EBIT | R4: VE/Ingresos | S4: P/U | T4: D/P calculado
A5: Universal Mobile | B5: 118496.87 | C5: 69130 | D5: 0.36844404 | E5: 0.58339095 | F5: 0.86 | G5: 43882 | H5: 11795 | I5: 16949 | J5: 3794 | K5: =C5/(B5+C5) -> 0.36844404 | L5: =H5/G5 -> 0.26878903 | M5: =I5/G5 -> 0.38624037 | N5: =J5/G5 -> 0.08645914 | O5: =B5+C5 -> 187626.87 | P5: =O5/I5 -> 11.070085 | Q5: =O5/H5 -> 15.907322 | R5: =O5/G5 -> 4.2757137 | S5: =IF(J5>0,B5/J5,"n.s.") -> 31.232701 | T5: =C5/B5 -> 0.58339095
A6: Neuberger Wireless | B6: 189469.95 | C6: 79351.251 | D6: 0.29518227 | E6: 0.41880653 | F6: 0.89 | G6: 42684 | H6: 7020 | I6: 14099 | J6: 4102.8 | K6: =C6/(B6+C6) -> 0.29518227 | L6: =H6/G6 -> 0.16446444 | M6: =I6/G6 -> 0.33031112 | N6: =J6/G6 -> 0.096120326 | O6: =B6+C6 -> 268821.2 | P6: =O6/I6 -> 19.066686 | Q6: =O6/H6 -> 38.293618 | R6: =O6/G6 -> 6.2979383 | S6: =IF(J6>0,B6/J6,"n.s.") -> 46.180645 | T6: =C6/B6 -> 0.41880653
A7: Agile Connections | B7: 21078.873 | C7: 5080.0084 | D7: 0.19419823 | E7: 0.241 | F7: 1.17 | G7: 34698 | H7: 1631.2202 | I7: 9914 | J7: -29.742 | K7: =C7/(B7+C7) -> 0.19419823 | L7: =H7/G7 -> 0.047011937 | M7: =I7/G7 -> 0.28572252 | N7: =J7/G7 -> -0.00085716756 | O7: =B7+C7 -> 26158.881 | P7: =O7/I7 -> 2.6385799 | Q7: =O7/H7 -> 16.036389 | R7: =O7/G7 -> 0.75390171 | S7: =IF(J7>0,B7/J7,"n.s.") -> n.s. | T7: =C7/B7 -> 0.241
A8: Big Country Communications | B8: 26285.355 | C8: 8335.086 | D8: 0.24075621 | E8: 0.3171 | F8: 0.97 | G8: 38896.458 | H8: 6701.8597 | I8: 12614.121 | J8: 3383.9918 | K8: =C8/(B8+C8) -> 0.24075621 | L8: =H8/G8 -> 0.1723 | M8: =I8/G8 -> 0.3243 | N8: =J8/G8 -> 0.087 | O8: =B8+C8 -> 34620.441 | P8: =O8/I8 -> 2.7445781 | Q8: =O8/H8 -> 5.1657961 | R8: =O8/G8 -> 0.89006666 | S8: =IF(J8>0,B8/J8,"n.s.") -> 7.7675585 | T8: =C8/B8 -> 0.3171
A9: Rocky Mountain Wireless | B9: 7359.8993 | C9: 3267.7953 | D9: 0.30747922 | E9: 0.444 | F9: 1.13 | G9: 4063.519 | H9: 510.0529 | I9: 1028.4767 | J9: 239.74762 | K9: =C9/(B9+C9) -> 0.30747922 | L9: =H9/G9 -> 0.12552 | M9: =I9/G9 -> 0.2531 | N9: =J9/G9 -> 0.059 | O9: =B9+C9 -> 10627.695 | P9: =O9/I9 -> 10.333433 | Q9: =O9/H9 -> 20.836455 | R9: =O9/G9 -> 2.6153919 | S9: =IF(J9>0,B9/J9,"n.s.") -> 30.698529 | T9: =C9/B9 -> 0.444
A11: Promedio | D11: =AVERAGE(D5:D9) -> 0.28121199 | E11: =AVERAGE(E5:E9) -> 0.4008595 | F11: =AVERAGE(F5:F9) -> 1.004 | K11: =AVERAGE(K5:K9) -> 0.28121199 | L11: =AVERAGE(L5:L9) -> 0.15561708 | M11: =AVERAGE(M5:M9) -> 0.3159348 | N11: =AVERAGE(N5:N9) -> 0.06554446 | P11: =AVERAGE(P5:P9) -> 9.1706723 | Q11: =AVERAGE(Q5:Q9) -> 19.247916 | R11: =AVERAGE(R5:R9) -> 2.9666024 | S11: =AVERAGE(S5:S9) -> 28.969858 | T11: =AVERAGE(T5:T9) -> 0.4008595
A12: D/P promedio publicado (referencia para indicadores) | I12: =E11 -> 0.4008595
A13: Mediana | D13: =MEDIAN(D5:D9) -> 0.29518227 | E13: =MEDIAN(E5:E9) -> 0.41880653 | F13: =MEDIAN(F5:F9) -> 0.97 | K13: =MEDIAN(K5:K9) -> 0.29518227 | L13: =MEDIAN(L5:L9) -> 0.16446444 | M13: =MEDIAN(M5:M9) -> 0.3243 | N13: =MEDIAN(N5:N9) -> 0.08645914 | P13: =MEDIAN(P5:P9) -> 10.333433 | Q13: =MEDIAN(Q5:Q9) -> 16.036389 | R13: =MEDIAN(R5:R9) -> 2.6153919 | S13: =MEDIAN(S5:S9) -> 30.965615 | T13: =MEDIAN(T5:T9) -> 0.41880653
A14: Tabla 3 publicada (promedio de márgenes) | L14: 0.156 | M14: 0.316 | N14: 0.066
A15: Control: diferencia Tabla 3 vs. recalculado | L15: =L14-L11 -> 0.00038292034 | M15: =M14-M11 -> 6.5196892e-05 | N15: =N14-N11 -> 0.0004555402 | O15: =MAX(ABS(L15),ABS(M15),ABS(N15)) -> 0.0004555402
A16: Control: D/V publicado − calculado (máx.) | O16: =MAX(ABS(D5-K5),ABS(D6-K6),ABS(D7-K7),ABS(D8-K8),ABS(D9-K9)) -> 0
A17: Inconsistencia: D/P promedio publicado vs. D/P implícito en el D/V promedio | D17: =D11/(1-D11) -> 0.39123078 | E17: =E11 -> 0.4008595
A18: AirThread 2007 (Tabla 3: EBIT 11,4%, EBITDA 26,2%, neto 8,0%) | L18: =Historicos!E105 -> 0.1142995 | M18: =Historicos!E104 -> 0.26184893 | N18: =Historicos!E106 -> 0.079754928
A21: Betas desapalancadas por empresa
B22: E/V | C22: 1 Hamada (βd=0) | D22: 2 Harris-Pringle (βd=0) | E22: 3 Harris-Pringle (βd>0)
A23: =A5 -> Universal Mobile | B23: =1-K5 -> 0.63155596 | C23: =F5/(1+(1-Supuestos!$C$6)*T5) -> 0.63702072 | D23: =F5*B23 -> 0.54313813 | E23: =F5*B23+Costo_Capital!$C$7*K5 -> 0.63524914
A24: =A6 -> Neuberger Wireless | B24: =1-K6 -> 0.70481773 | C24: =F6/(1+(1-Supuestos!$C$6)*T6) -> 0.71126943 | D24: =F6*B24 -> 0.62728778 | E24: =F6*B24+Costo_Capital!$C$7*K6 -> 0.70108335
A25: =A7 -> Agile Connections | B25: =1-K7 -> 0.80580177 | C25: =F7/(1+(1-Supuestos!$C$6)*T7) -> 1.0221912 | D25: =F7*B25 -> 0.94278807 | E25: =F7*B25+Costo_Capital!$C$7*K7 -> 0.99133763
A26: =A8 -> Big Country Communications | B26: =1-K8 -> 0.75924379 | C26: =F8/(1+(1-Supuestos!$C$6)*T8) -> 0.81494799 | D26: =F8*B26 -> 0.73646648 | E26: =F8*B26+Costo_Capital!$C$7*K8 -> 0.79665553
A27: =A9 -> Rocky Mountain Wireless | B27: =1-K9 -> 0.69252078 | C27: =F9/(1+(1-Supuestos!$C$6)*T9) -> 0.89229311 | D27: =F9*B27 -> 0.78254848 | E27: =F9*B27+Costo_Capital!$C$7*K9 -> 0.85941828
A28: Promedio | B28: =AVERAGE(B23:B27) -> 0.71878801 | C28: =AVERAGE(C23:C27) -> 0.81554448 | D28: =AVERAGE(D23:D27) -> 0.72644579 | E28: =AVERAGE(E23:E27) -> 0.79674879
A29: Mediana | C29: =MEDIAN(C23:C27) -> 0.81494799 | D29: =MEDIAN(D23:D27) -> 0.73646648 | E29: =MEDIAN(E23:E27) -> 0.79665553
A30: Nota: se usan D/V y D/P calculados con deuda neta, como en el anexo; el anexo aclara que reflejan promedios de 3 años.

Sheet Costo_Capital
A1: Costo de capital: insumos, opciones y elección
A3: A. Insumos elegidos
A4: Tasa libre de riesgo (Tesoro 10 años) | C4: =Supuestos!$C$9 -> 0.0425
A5: Prima de riesgo de mercado | C5: =Supuestos!$C$10 -> 0.05
A6: Costo de la deuda antes de impuestos (Kd) | C6: =Supuestos!$C$7 -> 0.055
A7: Beta de la deuda implícita en el CAPM = (Kd − rf) / PRM | C7: =(C6-C4)/C5 -> 0.25 | H7: Kd = rf + βd × PRM ⇒ βd = 0,25. La deuda BBB+ tiene riesgo sistemático; ignorarlo subestima Ku.
A8: Tasa de impuestos | C8: =Supuestos!$C$6 -> 0.4
A9: Beta desapalancada (activos) según selector | C9: =CHOOSE(Supuestos!$C$22,Comparables!C28,Comparables!D28,Comparables!E28) -> 0.79674879
A10: Costo de capital no apalancado Ku = rf + βu × PRM | C10: =C4+C9*C5 -> 0.082337439
A11: Estructura objetivo D/V (post 2012, valor terminal) | C11: =CHOOSE(Supuestos!$C$23,Comparables!$D$11,Comparables!$D$13,Supuestos!$C$12) -> 0.28121199
A12: D/P objetivo = L / (1 − L) | C12: =C11/(1-C11) -> 0.39123078
A13: Beta de la deuda usada al reapalancar | C13: =IF(Supuestos!$C$22=3,C7,0) -> 0.25
A14: Beta del patrimonio reapalancada | C14: =IF(Supuestos!$C$22=1,C9*(1+(1-C8)*C12),C9+(C9-C13)*C12) -> 1.0106537
A15: Costo del patrimonio Ke = rf + βe × PRM | C15: =C4+C14*C5 -> 0.093032687
A16: CPPC (WACC) objetivo = E/V × Ke + D/V × Kd × (1 − t) | C16: =(1-C11)*C15+C11*C6*(1-C8) -> 0.076150776
A17: Control (solo Harris-Pringle): Ku − t × Kd × D/V | C17: =C10-C8*C6*C11 -> 0.076150776
A18: Prima por tamaño | C18: 0 | H18: El caso no da primas por tamaño, regulación ni país: se dejan en 0 (ver justificación en la sección B).
A19: Prima por riesgo regulatorio | C19: 0
A20: Prima por riesgo país | C20: 0
A22: B. Opciones defendibles por insumo y su efecto en el valor del patrimonio (millones de US$)
A23: Insumo / opción | C23: Valor | D23: Ku | E23: CPPC objetivo | F23: Patrimonio | G23: Δ vs. base | H23: Fuente / comentario
A24: Beta: 1 Hamada, βd = 0 | C24: =Comparables!$C$28 -> 0.81554448 | D24: =$C$4+C24*$C$5 -> 0.083277224 | E24: =(1-$C$11)*($C$4+C24*(1+(1-$C$8)*$C$12)*$C$5)+$C$11*$C$6*(1-$C$8) -> 0.076018893 | F24: =NPV(D24,Proyeccion!$D$28:$H$28)+Proyeccion!$H$40+Proyeccion!$I$28/((E24)-Proyeccion!$H$34)/(1+D24)^5+Valoracion!$C$20-Valoracion!$C$26 -> 6747.8895 | G24: =F24-Valoracion!$C$33 -> -10.454171 | H24: Supone deuda fija y sin riesgo; incoherente con Kd > rf.
A25: Beta: 2 Harris-Pringle, βd = 0 | C25: =Comparables!$D$28 -> 0.72644579 | D25: =$C$4+C25*$C$5 -> 0.078822289 | E25: =$C$4+C25*$C$5-$C$8*$C$6*$C$11 -> 0.072635626 | F25: =NPV(D25,Proyeccion!$D$28:$H$28)+Proyeccion!$H$40+Proyeccion!$I$28/((E25)-Proyeccion!$H$34)/(1+D25)^5+Valoracion!$C$20-Valoracion!$C$26 -> 7208.3436 | G25: =F25-Valoracion!$C$33 -> 449.9999 | H25: Deuda reequilibrada; ignora el riesgo de la deuda.
A26: Beta: 3 Harris-Pringle, βd = 0,25 (elegida) | C26: =Comparables!$E$28 -> 0.79674879 | D26: =$C$4+C26*$C$5 -> 0.082337439 | E26: =$C$4+C26*$C$5-$C$8*$C$6*$C$11 -> 0.076150776 | F26: =NPV(D26,Proyeccion!$D$28:$H$28)+Proyeccion!$H$40+Proyeccion!$I$28/((E26)-Proyeccion!$H$34)/(1+D26)^5+Valoracion!$C$20-Valoracion!$C$26 -> 6758.3437 | G26: =F26-Valoracion!$C$33 -> 0 | H26: Coherente con Kd = 5,5% y con un valor terminal a CPPC con deuda reequilibrada.
A27: PRM 4% (supuesto propio, sensibilidad) | C27: 0.04 | D27: =$C$4+C27*Comparables!$D$28+($C$6-$C$4)*(1-Comparables!$B$28) -> 0.075072981 | E27: =D27-$C$8*$C$6*$C$11 -> 0.068886318 | F27: =NPV(D27,Proyeccion!$D$28:$H$28)+Proyeccion!$H$40+Proyeccion!$I$28/((E27)-Proyeccion!$H$34)/(1+D27)^5+Valoracion!$C$20-Valoracion!$C$26 -> 7773.0706 | G27: =F27-Valoracion!$C$33 -> 1014.7269 | H27: El caso solo da 5%. Ku = rf + PRM × promedio(E/V × βe) + (Kd − rf) × D/V promedio (método 3).
A28: PRM 6% (supuesto propio, sensibilidad) | C28: 0.06 | D28: =$C$4+C28*Comparables!$D$28+($C$6-$C$4)*(1-Comparables!$B$28) -> 0.089601897 | E28: =D28-$C$8*$C$6*$C$11 -> 0.083415233 | F28: =NPV(D28,Proyeccion!$D$28:$H$28)+Proyeccion!$H$40+Proyeccion!$I$28/((E28)-Proyeccion!$H$34)/(1+D28)^5+Valoracion!$C$20-Valoracion!$C$26 -> 6008.3836 | G28: =F28-Valoracion!$C$33 -> -749.96013 | H28: Ídem.
A29: D/V objetivo: promedio comparables (elegida) | C29: =Comparables!$D$11 -> 0.28121199 | D29: =$C$10 -> 0.082337439 | E29: =$C$10-$C$8*$C$6*C29 -> 0.076150776 | F29: =NPV(D29,Proyeccion!$D$28:$H$28)+Proyeccion!$H$40+Proyeccion!$I$28/((E29)-Proyeccion!$H$34)/(1+D29)^5+Valoracion!$C$20-Valoracion!$C$26 -> 6758.3437 | G29: =F29-Valoracion!$C$33 -> 0 | H29: Anexo 7; el caso pide converger a la norma de la industria.
A30: D/V objetivo: mediana comparables | C30: =Comparables!$D$13 -> 0.29518227 | D30: =$C$10 -> 0.082337439 | E30: =$C$10-$C$8*$C$6*C30 -> 0.075843429 | F30: =NPV(D30,Proyeccion!$D$28:$H$28)+Proyeccion!$H$40+Proyeccion!$I$28/((E30)-Proyeccion!$H$34)/(1+D30)^5+Valoracion!$C$20-Valoracion!$C$26 -> 6787.5187 | G30: =F30-Valoracion!$C$33 -> 29.174965 | H30: Anexo 7.
A31: D/V objetivo: 50% (máximo de R&R) a perpetuidad | C31: =Supuestos!$C$12 -> 0.5 | D31: =$C$10 -> 0.082337439 | E31: =$C$10-$C$8*$C$6*C31 -> 0.071337439 | F31: =NPV(D31,Proyeccion!$D$28:$H$28)+Proyeccion!$H$40+Proyeccion!$I$28/((E31)-Proyeccion!$H$34)/(1+D31)^5+Valoracion!$C$20-Valoracion!$C$26 -> 7262.5416 | G31: =F31-Valoracion!$C$33 -> 504.19791 | H31: Agresivo: R&R lo plantea para la compra, no como estructura permanente.
A32: Primas por tamaño, regulación o país | C32: 0 | D32: =$C$10+C32 -> 0.082337439 | E32: =$C$16+C32 -> 0.076150776 | F32: =NPV(D32,Proyeccion!$D$28:$H$28)+Proyeccion!$H$40+Proyeccion!$I$28/((E32)-Proyeccion!$H$34)/(1+D32)^5+Valoracion!$C$20-Valoracion!$C$26 -> 6758.3437 | G32: =F32-Valoracion!$C$33 -> 0 | H32: No se suman: los comparables son operadores de EE. UU. con la misma regulación (FCC); el caso no da prima por tamaño.
A34: Variable decisiva: crecimiento a perpetuidad y método del valor terminal (ver hojas Sensibilidad y Valoracion).
A35: Moneda e inflación: flujos en US$ nominales; rf nominal en US$; el caso no da inflación. g nominal.
A36: Plazo de rf: 10 años, el único que da el caso; los flujos son perpetuos (un bono a 20-30 años sería más coherente).

Sheet Deuda
A1: Deuda de adquisición: préstamo amortizable a 10 años con pago bullet al mes 60 (Anexo 6)
A3: EBITDA 2007 | C3: =Historicos!E11 -> 1033.325 | E3: Anexo 6 publicado: deuda inicial 3.758, cuota 41, saldo antes del bullet 2.166.
A4: Intereses máximos = EBITDA / cobertura | C4: =C3/Supuestos!$C$11 -> 206.665
A5: Deuda inicial = intereses máximos / Kd | C5: =C4/Supuestos!$C$7 -> 3757.5455
A6: Cuota mensual (amortización a 120 meses) | C6: =PMT(Supuestos!$C$7/12,Supuestos!$C$13,-C5) -> 40.779242
A8: Mes | B8: Fecha | C8: Saldo inicial | D8: Cuota | E8: Interés | F8: Capital | G8: Pago bullet | H8: Saldo final | I8: Año | K8: Resumen anual | L8: 2008 | M8: 2009 | N8: 2010 | O8: 2011 | P8: 2012
A9: 1 | B9: =DATE(2008,A9+1,0) -> 39478 | C9: =C5 -> 3757.5455 | D9: =$C$6 -> 40.779242 | E9: =C9*Supuestos!$C$7/12 -> 17.222083 | F9: =D9-E9 -> 23.557159 | G9: =IF(A9=Supuestos!$C$14,C9-F9,0) -> 0 | H9: =C9-F9-G9 -> 3733.9883 | I9: =YEAR(B9) -> 2008 | K9: Intereses | L9: =SUMIF($I$9:$I$68,2008,$E$9:$E$68) -> 199.42896 | M9: =SUMIF($I$9:$I$68,2009,$E$9:$E$68) -> 183.07508 | N9: =SUMIF($I$9:$I$68,2010,$E$9:$E$68) -> 165.79872 | O9: =SUMIF($I$9:$I$68,2011,$E$9:$E$68) -> 147.54783 | P9: =SUMIF($I$9:$I$68,2012,$E$9:$E$68) -> 128.26745
A10: 2 | B10: =DATE(2008,A10+1,0) -> 39507 | C10: =H9 -> 3733.9883 | D10: =$C$6 -> 40.779242 | E10: =C10*Supuestos!$C$7/12 -> 17.114113 | F10: =D10-E10 -> 23.665129 | G10: =IF(A10=Supuestos!$C$14,C10-F10,0) -> 0 | H10: =C10-F10-G10 -> 3710.3232 | I10: =YEAR(B10) -> 2008 | K10: Amortización ordinaria de capital | L10: =SUMIF($I$9:$I$68,2008,$F$9:$F$68) -> 289.92195 | M10: =SUMIF($I$9:$I$68,2009,$F$9:$F$68) -> 306.27583 | N10: =SUMIF($I$9:$I$68,2010,$F$9:$F$68) -> 323.55219 | O10: =SUMIF($I$9:$I$68,2011,$F$9:$F$68) -> 341.80308 | P10: =SUMIF($I$9:$I$68,2012,$F$9:$F$68) -> 361.08346
A11: 3 | B11: =DATE(2008,A11+1,0) -> 39538 | C11: =H10 -> 3710.3232 | D11: =$C$6 -> 40.779242 | E11: =C11*Supuestos!$C$7/12 -> 17.005648 | F11: =D11-E11 -> 23.773594 | G11: =IF(A11=Supuestos!$C$14,C11-F11,0) -> 0 | H11: =C11-F11-G11 -> 3686.5496 | I11: =YEAR(B11) -> 2008 | K11: Pago bullet (refinanciado) | L11: =SUMIF($I$9:$I$68,2008,$G$9:$G$68) -> 0 | M11: =SUMIF($I$9:$I$68,2009,$G$9:$G$68) -> 0 | N11: =SUMIF($I$9:$I$68,2010,$G$9:$G$68) -> 0 | O11: =SUMIF($I$9:$I$68,2011,$G$9:$G$68) -> 0 | P11: =SUMIF($I$9:$I$68,2012,$G$9:$G$68) -> 2134.909
A12: 4 | B12: =DATE(2008,A12+1,0) -> 39568 | C12: =H11 -> 3686.5496 | D12: =$C$6 -> 40.779242 | E12: =C12*Supuestos!$C$7/12 -> 16.896686 | F12: =D12-E12 -> 23.882557 | G12: =IF(A12=Supuestos!$C$14,C12-F12,0) -> 0 | H12: =C12-F12-G12 -> 3662.667 | I12: =YEAR(B12) -> 2008 | K12: Saldo al cierre antes del bullet | L12: =INDEX($C$9:$C$68,12)-INDEX($F$9:$F$68,12) -> 3467.6235 | M12: =INDEX($C$9:$C$68,24)-INDEX($F$9:$F$68,24) -> 3161.3477 | N12: =INDEX($C$9:$C$68,36)-INDEX($F$9:$F$68,36) -> 2837.7955 | O12: =INDEX($C$9:$C$68,48)-INDEX($F$9:$F$68,48) -> 2495.9924 | P12: =INDEX($C$9:$C$68,60)-INDEX($F$9:$F$68,60) -> 2134.909
A13: 5 | B13: =DATE(2008,A13+1,0) -> 39599 | C13: =H12 -> 3662.667 | D13: =$C$6 -> 40.779242 | E13: =C13*Supuestos!$C$7/12 -> 16.787224 | F13: =D13-E13 -> 23.992018 | G13: =IF(A13=Supuestos!$C$14,C13-F13,0) -> 0 | H13: =C13-F13-G13 -> 3638.675 | I13: =YEAR(B13) -> 2008 | K13: Escudo fiscal = intereses × t | L13: =L9*Supuestos!$C$6 -> 79.771583 | M13: =M9*Supuestos!$C$6 -> 73.230033 | N13: =N9*Supuestos!$C$6 -> 66.319487 | O13: =O9*Supuestos!$C$6 -> 59.019132 | P13: =P9*Supuestos!$C$6 -> 51.30698
A14: 6 | B14: =DATE(2008,A14+1,0) -> 39629 | C14: =H13 -> 3638.675 | D14: =$C$6 -> 40.779242 | E14: =C14*Supuestos!$C$7/12 -> 16.67726 | F14: =D14-E14 -> 24.101982 | G14: =IF(A14=Supuestos!$C$14,C14-F14,0) -> 0 | H14: =C14-F14-G14 -> 3614.573 | I14: =YEAR(B14) -> 2008 | K14: Saldo publicado en el Anexo 6 | L14: 3468 | M14: 3161 | N14: 2838 | O14: 2496 | P14: 2166
A15: 7 | B15: =DATE(2008,A15+1,0) -> 39660 | C15: =H14 -> 3614.573 | D15: =$C$6 -> 40.779242 | E15: =C15*Supuestos!$C$7/12 -> 16.566793 | F15: =D15-E15 -> 24.212449 | G15: =IF(A15=Supuestos!$C$14,C15-F15,0) -> 0 | H15: =C15-F15-G15 -> 3590.3606 | I15: =YEAR(B15) -> 2008 | K15: Control: diferencia (fila 16 − fila 14) | L15: =L16-L14 -> -0.37649403 | M15: =M16-M14 -> 0.3476806 | N15: =N16-N14 -> -0.20450877 | O15: =O16-O14 -> -0.0075848637 | P15: =P16-P14 -> -0.23820713 | Q15: =MAX(ABS(L15),ABS(M15),ABS(N15),ABS(O15),ABS(P15)) -> 0.37649403
A16: 8 | B16: =DATE(2008,A16+1,0) -> 39691 | C16: =H15 -> 3590.3606 | D16: =$C$6 -> 40.779242 | E16: =C16*Supuestos!$C$7/12 -> 16.455819 | F16: =D16-E16 -> 24.323423 | G16: =IF(A16=Supuestos!$C$14,C16-F16,0) -> 0 | H16: =C16-F16-G16 -> 3566.0371 | I16: =YEAR(B16) -> 2008 | K16: Saldo comparable con el Anexo 6 (2012: inicio del mes 60) | L16: =INDEX($H$9:$H$68,12) -> 3467.6235 | M16: =INDEX($H$9:$H$68,24) -> 3161.3477 | N16: =INDEX($H$9:$H$68,36) -> 2837.7955 | O16: =INDEX($H$9:$H$68,48) -> 2495.9924 | P16: =INDEX($C$9:$C$68,60) -> 2165.7618
A17: 9 | B17: =DATE(2008,A17+1,0) -> 39721 | C17: =H16 -> 3566.0371 | D17: =$C$6 -> 40.779242 | E17: =C17*Supuestos!$C$7/12 -> 16.344337 | F17: =D17-E17 -> 24.434905 | G17: =IF(A17=Supuestos!$C$14,C17-F17,0) -> 0 | H17: =C17-F17-G17 -> 3541.6022 | I17: =YEAR(B17) -> 2008 | K17: Cobertura EBITDA 2007 / intereses del año 1 | L17: =C3/L9 -> 5.181419
A18: 10 | B18: =DATE(2008,A18+1,0) -> 39752 | C18: =H17 -> 3541.6022 | D18: =$C$6 -> 40.779242 | E18: =C18*Supuestos!$C$7/12 -> 16.232344 | F18: =D18-E18 -> 24.546899 | G18: =IF(A18=Supuestos!$C$14,C18-F18,0) -> 0 | H18: =C18-F18-G18 -> 3517.0553 | I18: =YEAR(B18) -> 2008 | K18: Nota: el Anexo 6 rotula 84 períodos restantes en el mes 41 (deberían ser 79); no afecta la cuota.
A19: 11 | B19: =DATE(2008,A19+1,0) -> 39782 | C19: =H18 -> 3517.0553 | D19: =$C$6 -> 40.779242 | E19: =C19*Supuestos!$C$7/12 -> 16.119837 | F19: =D19-E19 -> 24.659405 | G19: =IF(A19=Supuestos!$C$14,C19-F19,0) -> 0 | H19: =C19-F19-G19 -> 3492.3959 | I19: =YEAR(B19) -> 2008
A20: 12 | B20: =DATE(2008,A20+1,0) -> 39813 | C20: =H19 -> 3492.3959 | D20: =$C$6 -> 40.779242 | E20: =C20*Supuestos!$C$7/12 -> 16.006815 | F20: =D20-E20 -> 24.772428 | G20: =IF(A20=Supuestos!$C$14,C20-F20,0) -> 0 | H20: =C20-F20-G20 -> 3467.6235 | I20: =YEAR(B20) -> 2008
A21: 13 | B21: =DATE(2008,A21+1,0) -> 39844 | C21: =H20 -> 3467.6235 | D21: =$C$6 -> 40.779242 | E21: =C21*Supuestos!$C$7/12 -> 15.893274 | F21: =D21-E21 -> 24.885968 | G21: =IF(A21=Supuestos!$C$14,C21-F21,0) -> 0 | H21: =C21-F21-G21 -> 3442.7375 | I21: =YEAR(B21) -> 2009
A22: 14 | B22: =DATE(2008,A22+1,0) -> 39872 | C22: =H21 -> 3442.7375 | D22: =$C$6 -> 40.779242 | E22: =C22*Supuestos!$C$7/12 -> 15.779214 | F22: =D22-E22 -> 25.000029 | G22: =IF(A22=Supuestos!$C$14,C22-F22,0) -> 0 | H22: =C22-F22-G22 -> 3417.7375 | I22: =YEAR(B22) -> 2009
A23: 15 | B23: =DATE(2008,A23+1,0) -> 39903 | C23: =H22 -> 3417.7375 | D23: =$C$6 -> 40.779242 | E23: =C23*Supuestos!$C$7/12 -> 15.66463 | F23: =D23-E23 -> 25.114612 | G23: =IF(A23=Supuestos!$C$14,C23-F23,0) -> 0 | H23: =C23-F23-G23 -> 3392.6229 | I23: =YEAR(B23) -> 2009
A24: 16 | B24: =DATE(2008,A24+1,0) -> 39933 | C24: =H23 -> 3392.6229 | D24: =$C$6 -> 40.779242 | E24: =C24*Supuestos!$C$7/12 -> 15.549522 | F24: =D24-E24 -> 25.229721 | G24: =IF(A24=Supuestos!$C$14,C24-F24,0) -> 0 | H24: =C24-F24-G24 -> 3367.3932 | I24: =YEAR(B24) -> 2009
A25: 17 | B25: =DATE(2008,A25+1,0) -> 39964 | C25: =H24 -> 3367.3932 | D25: =$C$6 -> 40.779242 | E25: =C25*Supuestos!$C$7/12 -> 15.433885 | F25: =D25-E25 -> 25.345357 | G25: =IF(A25=Supuestos!$C$14,C25-F25,0) -> 0 | H25: =C25-F25-G25 -> 3342.0478 | I25: =YEAR(B25) -> 2009
A26: 18 | B26: =DATE(2008,A26+1,0) -> 39994 | C26: =H25 -> 3342.0478 | D26: =$C$6 -> 40.779242 | E26: =C26*Supuestos!$C$7/12 -> 15.317719 | F26: =D26-E26 -> 25.461523 | G26: =IF(A26=Supuestos!$C$14,C26-F26,0) -> 0 | H26: =C26-F26-G26 -> 3316.5863 | I26: =YEAR(B26) -> 2009
A27: 19 | B27: =DATE(2008,A27+1,0) -> 40025 | C27: =H26 -> 3316.5863 | D27: =$C$6 -> 40.779242 | E27: =C27*Supuestos!$C$7/12 -> 15.201021 | F27: =D27-E27 -> 25.578222 | G27: =IF(A27=Supuestos!$C$14,C27-F27,0) -> 0 | H27: =C27-F27-G27 -> 3291.0081 | I27: =YEAR(B27) -> 2009
A28: 20 | B28: =DATE(2008,A28+1,0) -> 40056 | C28: =H27 -> 3291.0081 | D28: =$C$6 -> 40.779242 | E28: =C28*Supuestos!$C$7/12 -> 15.083787 | F28: =D28-E28 -> 25.695455 | G28: =IF(A28=Supuestos!$C$14,C28-F28,0) -> 0 | H28: =C28-F28-G28 -> 3265.3126 | I28: =YEAR(B28) -> 2009
A29: 21 | B29: =DATE(2008,A29+1,0) -> 40086 | C29: =H28 -> 3265.3126 | D29: =$C$6 -> 40.779242 | E29: =C29*Supuestos!$C$7/12 -> 14.966016 | F29: =D29-E29 -> 25.813226 | G29: =IF(A29=Supuestos!$C$14,C29-F29,0) -> 0 | H29: =C29-F29-G29 -> 3239.4994 | I29: =YEAR(B29) -> 2009
A30: 22 | B30: =DATE(2008,A30+1,0) -> 40117 | C30: =H29 -> 3239.4994 | D30: =$C$6 -> 40.779242 | E30: =C30*Supuestos!$C$7/12 -> 14.847706 | F30: =D30-E30 -> 25.931537 | G30: =IF(A30=Supuestos!$C$14,C30-F30,0) -> 0 | H30: =C30-F30-G30 -> 3213.5679 | I30: =YEAR(B30) -> 2009
... A68: 60 | B68: =DATE(2008,A68+1,0) -> 41274 | C68: =H67 -> 2165.7618 | D68: =$C$6 -> 40.779242 | E68: =C68*Supuestos!$C$7/12 -> 9.9264082 | F68: =D68-E68 -> 30.852834 | G68: =IF(A68=Supuestos!$C$14,C68-F68,0) -> 2134.909 | H68: =C68-F68-G68 -> 0 | I68: =YEAR(B68) -> 2012

Sheet Proyeccion
A1: Proyección 2008-2012 sin sinergias y estados financieros proforma (millones de US$)
A3: Flujo de caja libre (escenario base)
A4: Año | C4: 2007 real | D4: 2008 | E4: 2009 | F4: 2010 | G4: 2011 | H4: 2012 | I4: 2013 normal.
A5: Ingresos por servicios | C5: =Historicos!$E$5 -> 3679.237 | D5: =C5*(1+D6) -> 4194.3302 | E5: =D5*(1+E6) -> 4781.5364 | F5: =E5*(1+F6) -> 5379.2285 | G5: =F5*(1+G6) -> 5917.1513 | H5: =G5*(1+H6) -> 6331.3519
A6: Crecimiento de ingresos por servicios | C6: =Historicos!$E$103 -> 0.14460725 | D6: =Supuestos!D$36+Supuestos!$C$63 -> 0.14 | E6: =Supuestos!E$36+Supuestos!$C$63 -> 0.14 | F6: =Supuestos!F$36+Supuestos!$C$63 -> 0.125 | G6: =Supuestos!G$36+Supuestos!$C$63 -> 0.1 | H6: =Supuestos!H$36+Supuestos!$C$63 -> 0.07
A7: Ingresos por equipos | C7: =Historicos!$E$6 -> 267.027 | D7: =D5*Supuestos!$C$45 -> 314.77315 | E7: =E5*Supuestos!$C$45 -> 358.84139 | F7: =F5*Supuestos!$C$45 -> 403.69657 | G7: =G5*Supuestos!$C$45 -> 444.06622 | H7: =H5*Supuestos!$C$45 -> 475.15086
A8: Ingresos totales | C8: =Historicos!$E$7 -> 3946.264 | D8: =D5+D7 -> 4509.1033 | E8: =E5+E7 -> 5140.3778 | F8: =F5+F7 -> 5782.925 | G8: =G5+G7 -> 6361.2175 | H8: =H5+H7 -> 6806.5027
A9: Costos de operación del sistema | C9: =Historicos!$E$8 -> 717.075 | D9: =D5*Supuestos!D$37 -> 838.86604 | E9: =E5*Supuestos!E$37 -> 956.30728 | F9: =F5*Supuestos!F$37 -> 1075.8457 | G9: =G5*Supuestos!G$37 -> 1183.4303 | H9: =H5*Supuestos!H$37 -> 1266.2704
A10: Costo de equipos vendidos | C10: =Historicos!$E$9 -> 640.225 | D10: =D7*Supuestos!D$38 -> 755.45556 | E10: =E7*Supuestos!E$38 -> 861.21934 | F10: =F7*Supuestos!F$38 -> 968.87176 | G10: =G7*Supuestos!G$38 -> 1065.7589 | H10: =H7*Supuestos!H$38 -> 1140.3621
A11: SG&A | C11: =Historicos!$E$10 -> 1555.639 | D11: =D8*(Supuestos!D$39+Supuestos!$C$64) -> 1803.6413 | E11: =E8*(Supuestos!E$39+Supuestos!$C$64) -> 2056.1511 | F11: =F8*(Supuestos!F$39+Supuestos!$C$64) -> 2313.17 | G11: =G8*(Supuestos!G$39+Supuestos!$C$64) -> 2544.487 | H11: =H8*(Supuestos!H$39+Supuestos!$C$64) -> 2722.6011
A12: EBITDA | C12: =Historicos!$E$11 -> 1033.325 | D12: =D8-D9-D10-D11 -> 1111.1404 | E12: =E8-E9-E10-E11 -> 1266.7001 | F12: =F8-F9-F10-F11 -> 1425.0376 | G12: =G8-G9-G10-G11 -> 1567.5413 | H12: =H8-H9-H10-H11 -> 1677.2692
A13: Margen EBITDA | C13: =C12/C8 -> 0.26184893 | D13: =D12/D8 -> 0.24642159 | E13: =E12/E8 -> 0.24642159 | F13: =F12/F8 -> 0.24642159 | G13: =G12/G8 -> 0.24642159 | H13: =H12/H8 -> 0.24642159
A14: Depreciación y amortización | C14: =Historicos!$E$12 -> 582.269 | D14: =D8*Supuestos!D$42 -> 705.22932 | E14: =E8*Supuestos!E$42 -> 803.96142 | F14: =F8*Supuestos!F$42 -> 867.43875 | G14: =G8*Supuestos!G$42 -> 922.37654 | H14: =H8*Supuestos!H$42 -> 952.91038
A15: EBIT | C15: =Historicos!$E$13 -> 451.056 | D15: =D12-D14 -> 405.91108 | E15: =E12-E14 -> 462.73863 | F15: =F12-F14 -> 557.59881 | G15: =G12-G14 -> 645.16478 | H15: =H12-H14 -> 724.35883
A16: Impuestos operativos (EBIT × t) | D16: =D15*Supuestos!$C$6 -> 162.36443 | E16: =E15*Supuestos!$C$6 -> 185.09545 | F16: =F15*Supuestos!$C$6 -> 223.03952 | G16: =G15*Supuestos!$C$6 -> 258.06591 | H16: =H15*Supuestos!$C$6 -> 289.74353
A17: Utilidad operativa después de impuestos (NOPAT) | D17: =D15-D16 -> 243.54665 | E17: =E15-E16 -> 277.64318 | F17: =F15-F16 -> 334.55929 | G17: =G15-G16 -> 387.09887 | H17: =H15-H16 -> 434.6153 | I17: =H17*(1+H34) -> 446.69807
A18: Costos operativos en efectivo | C18: =C9+C10+C11 -> 2912.939 | D18: =D9+D10+D11 -> 3397.9629 | E18: =E9+E10+E11 -> 3873.6777 | F18: =F9+F10+F11 -> 4357.8875 | G18: =G9+G10+G11 -> 4793.6762 | H18: =H9+H10+H11 -> 5129.2335
A19: Cuentas por cobrar | C19: =Historicos!$E$37 -> 435.497 | D19: =D8*Supuestos!$C$46/360 -> 521.89513 | E19: =E8*Supuestos!$C$46/360 -> 594.96044 | F19: =F8*Supuestos!$C$46/360 -> 669.3305 | G19: =G8*Supuestos!$C$46/360 -> 736.26355 | H19: =H8*Supuestos!$C$46/360 -> 787.802
A20: Inventario | C20: =Historicos!$E$38 -> 100.99 | D20: =D7*Supuestos!$C$47/360 -> 134.96792 | E20: =E7*Supuestos!$C$47/360 -> 153.86343 | F20: =F7*Supuestos!$C$47/360 -> 173.09635 | G20: =G7*Supuestos!$C$47/360 -> 190.40599 | H20: =H7*Supuestos!$C$47/360 -> 203.73441
A21: Gastos prepagados | C21: =Historicos!$E$39 -> 41.588 | D21: =D18*Supuestos!$C$48 -> 46.914828 | E21: =E18*Supuestos!$C$48 -> 53.482904 | F21: =F18*Supuestos!$C$48 -> 60.168267 | G21: =G18*Supuestos!$C$48 -> 66.185093 | H21: =H18*Supuestos!$C$48 -> 70.81805
A22: Cuentas por pagar | C22: =Historicos!$E$52 -> 260.791 | D22: =D18*Supuestos!$C$49/360 -> 335.42132 | E22: =E18*Supuestos!$C$49/360 -> 382.3803 | F22: =F18*Supuestos!$C$49/360 -> 430.17784 | G22: =G18*Supuestos!$C$49/360 -> 473.19563 | H22: =H18*Supuestos!$C$49/360 -> 506.31932
A23: Ingresos diferidos | C23: =Historicos!$E$53 -> 143.445 | D23: =D5*Supuestos!$C$50/360 -> 163.25425 | E23: =E5*Supuestos!$C$50/360 -> 186.10984 | F23: =F5*Supuestos!$C$50/360 -> 209.37357 | G23: =G5*Supuestos!$C$50/360 -> 230.31093 | H23: =H5*Supuestos!$C$50/360 -> 246.43269
A24: Pasivos acumulados | C24: =Historicos!$E$54 -> 59.224 | D24: =D18*Supuestos!$C$51/360 -> 64.60904 | E24: =E18*Supuestos!$C$51/360 -> 73.654305 | F24: =F18*Supuestos!$C$51/360 -> 82.861094 | G24: =G18*Supuestos!$C$51/360 -> 91.147203 | H24: =H18*Supuestos!$C$51/360 -> 97.527507
A25: Capital de trabajo operativo neto | C25: =C19+C20+C21-C22-C23-C24 -> 114.615 | D25: =D19+D20+D21-D22-D23-D24 -> 140.49327 | E25: =E19+E20+E21-E22-E23-E24 -> 160.16232 | F25: =F19+F20+F21-F22-F23-F24 -> 180.18261 | G25: =G19+G20+G21-G22-G23-G24 -> 198.20087 | H25: =H19+H20+H21-H22-H23-H24 -> 212.07494
A26: Aumento del capital de trabajo operativo neto | D26: =D25-C25 -> 25.878265 | E26: =E25-D25 -> 19.669057 | F26: =F25-E25 -> 20.02029 | G26: =G25-F25 -> 18.018261 | H26: =H25-G25 -> 13.874061
A27: Capex | D27: =D8*(Supuestos!D$41+Supuestos!$C$65) -> 631.27447 | E27: =E8*(Supuestos!E$41+Supuestos!$C$65) -> 719.65289 | F27: =F8*(Supuestos!F$41+Supuestos!$C$65) -> 867.43875 | G27: =G8*(Supuestos!G$41+Supuestos!$C$65) -> 970.08567 | H27: =H8*(Supuestos!H$41+Supuestos!$C$65) -> 1055.0079
A28: Flujo de caja libre no apalancado | D28: =D17+D14-D27-D26 -> 291.62324 | E28: =E17+E14-E27-E26 -> 342.28266 | F28: =F17+F14-F27-F26 -> 314.539 | G28: =G17+G14-G27-G26 -> 321.37148 | H28: =H17+H14-H27-H26 -> 318.6437 | I28: =I17*(1-H35) -> 327.50233
A29: Capital invertido contable (patrimonio + deuda) | C29: =Historicos!$E$90+Historicos!$E$62+Historicos!$E$57 -> 4198.449 | D29: =C29+D27-D14+D26 -> 4150.3724 | E29: =D29+E27-E14+E26 -> 4085.7329 | F29: =E29+F27-F14+F26 -> 4105.7532 | G29: =F29+G27-G14+G26 -> 4171.4806 | H29: =G29+H27-H14+H26 -> 4287.4522
A30: ROIC (NOPAT / capital invertido al inicio del año) | D30: =D17/C29 -> 0.058008719 | E30: =E17/D29 -> 0.066895968 | F30: =F17/E29 -> 0.081884766 | G30: =G17/F29 -> 0.094282059 | H30: =H17/G29 -> 0.1041873
A31: Tasa de reinversión = (capex − D&A + Δ capital de trabajo) / NOPAT | D31: =(D27-D14+D26)/D17 -> -0.19740197 | E31: =(E27-E14+E26)/E17 -> -0.23281492 | F31: =(F27-F14+F26)/F17 -> 0.059840785 | G31: =(G27-G14+G26)/G17 -> 0.16979485 | H31: =(H27-H14+H26)/H17 -> 0.26683737
A33: Crecimiento fundamental = ROIC 2012 × tasa de reinversión 2012 | H33: =H30*H31 -> 0.027801065
A34: Crecimiento a perpetuidad usado (g) | H34: =IF(Supuestos!$C$24=1,H33,Supuestos!$C$25) -> 0.027801065
A35: Tasa de reinversión de largo plazo = g / ROIC 2012 | H35: =H34/H30 -> 0.26683737
A36: Valor terminal 2012 = FCF 2013 / (CPPC − g) | H36: =I28/(Costo_Capital!$C$16-H34) -> 6773.615
A37: Valor terminal 2012 por múltiplo VE/EBITDA (contraste) | H37: =H12*IF(Supuestos!$C$26=1,Comparables!$P$11,Comparables!$P$13) -> 17331.949
A38: VP de los FCF 2008-2012 a Ku | H38: =NPV(Costo_Capital!$C$10,D28:H28) -> 1258.417
A39: VP del valor terminal a Ku | H39: =H36/(1+Costo_Capital!$C$10)^5 -> 4560.4438
A40: VP de los escudos fiscales 2008-2012 a Kd | H40: =NPV(Supuestos!$C$7,Deuda!$L$13:$P$13) -> 284.78312
A41: Valor de las operaciones (APV) | H41: =H38+H39+H40 -> 6103.6439
A42: + Activos no operativos | H42: =Valoracion!$C$20 -> 1944.4871
A43: − Deuda existente e interés minoritario | H43: =Valoracion!$C$26 -> 1289.7873
A44: Valor del patrimonio (100%, antes de descuento por iliquidez) | H44: =H41+H42-H43 -> 6758.3437
A47: Estados financieros proforma con la deuda de adquisición (variable de cierre: caja / línea de crédito)
C48: 2007 proforma | D48: 2008 | E48: 2009 | F48: 2010 | G48: 2011 | H48: 2012 | J48: Supuestos del proforma
A49: EBIT | C49: =C15 -> 451.056 | D49: =D15 -> 405.91108 | E49: =E15 -> 462.73863 | F49: =F15 -> 557.59881 | G49: =G15 -> 645.16478 | H49: =H15 -> 724.35883 | J49: Solo operaciones: no se proyectan afiliadas, ganancias en inversiones, otros ingresos ni interés minoritario (se valoran aparte).
A50: Intereses de la deuda de adquisición | D50: =Deuda!L$9 -> 199.42896 | E50: =Deuda!M$9 -> 183.07508 | F50: =Deuda!N$9 -> 165.79872 | G50: =Deuda!O$9 -> 147.54783 | H50: =Deuda!P$9 -> 128.26745 | J50: La deuda existente (1.002) se refinancia con la deuda de adquisición (3.758).
A51: Intereses de la línea de crédito (Kd sobre saldo inicial) | D51: =C70*Supuestos!$C$7 -> 0 | E51: =D70*Supuestos!$C$7 -> 6.4875847 | F51: =E70*Supuestos!$C$7 -> 10.762777 | G51: =F70*Supuestos!$C$7 -> 17.085032 | H51: =G70*Supuestos!$C$7 -> 23.641654 | J51: Caja inicial 0: la caja de 2007 se usa en la compra. La caja no genera intereses (conservador).
A52: Utilidad antes de impuestos | D52: =D49-D50-D51 -> 206.48212 | E52: =E49-E50-E51 -> 273.17597 | F52: =F49-F50-F51 -> 381.03732 | G52: =G49-G50-G51 -> 480.53192 | H52: =H49-H50-H51 -> 572.44972 | J52: Sin dividendos: todo el excedente queda como caja; los faltantes los cubre la línea de crédito a Kd.
A53: Impuestos | D53: =D52*Supuestos!$C$6 -> 82.592849 | E53: =E52*Supuestos!$C$6 -> 109.27039 | F53: =F52*Supuestos!$C$6 -> 152.41493 | G53: =G52*Supuestos!$C$6 -> 192.21277 | H53: =H52*Supuestos!$C$6 -> 228.97989 | J53: En 2012 el saldo bullet se refinancia (no sale caja); a partir de ahí la deuda sigue la estructura objetivo.
A54: Utilidad neta (solo operaciones) | D54: =D52-D53 -> 123.88927 | E54: =E52-E53 -> 163.90558 | F54: =F52-F53 -> 228.62239 | G54: =G52-G53 -> 288.31915 | H54: =H52-H53 -> 343.46983
A56: Caja | C56: 0 | D56: =MAX(0,D84) -> 0 | E56: =MAX(0,E84) -> 0 | F56: =MAX(0,F84) -> 0 | G56: =MAX(0,G84) -> 0 | H56: =MAX(0,H84) -> 0
A57: Cuentas por cobrar | C57: =C19 -> 435.497 | D57: =D19 -> 521.89513 | E57: =E19 -> 594.96044 | F57: =F19 -> 669.3305 | G57: =G19 -> 736.26355 | H57: =H19 -> 787.802
A58: Inventario | C58: =C20 -> 100.99 | D58: =D20 -> 134.96792 | E58: =E20 -> 153.86343 | F58: =F20 -> 173.09635 | G58: =G20 -> 190.40599 | H58: =H20 -> 203.73441
A59: Gastos prepagados | C59: =C21 -> 41.588 | D59: =D21 -> 46.914828 | E59: =E21 -> 53.482904 | F59: =F21 -> 60.168267 | G59: =G21 -> 66.185093 | H59: =H21 -> 70.81805
A60: Otros activos corrientes e impuestos diferidos (constantes) | C60: =Historicos!$E$41+Historicos!$E$40 -> 34.793 | D60: =C60 -> 34.793 | E60: =D60 -> 34.793 | F60: =E60 -> 34.793 | G60: =F60 -> 34.793 | H60: =G60 -> 34.793
A61: Activo fijo neto, licencias y listas de clientes | C61: =Historicos!$E$96 -> 4092.917 | D61: =C61+D27-D14 -> 4018.9621 | E61: =D61+E27-E14 -> 3934.6536 | F61: =E61+F27-F14 -> 3934.6536 | G61: =F61+G27-G14 -> 3982.3627 | H61: =G61+H27-H14 -> 4084.4603
A62: Plusvalía (constante) | C62: =Historicos!$E$49 -> 491.316 | D62: =C62 -> 491.316 | E62: =D62 -> 491.316 | F62: =E62 -> 491.316 | G62: =F62 -> 491.316 | H62: =G62 -> 491.316
A63: Afiliadas, nota por cobrar y otros activos LP (constantes) | C63: =Historicos!$E$47+Historicos!$E$48+Historicos!$E$50+Historicos!$E$46 -> 193.888 | D63: =C63 -> 193.888 | E63: =D63 -> 193.888 | F63: =E63 -> 193.888 | G63: =F63 -> 193.888 | H63: =G63 -> 193.888
A64: Total activos | C64: =C56+C57+C58+C59+C60+C61+C62+C63 -> 5390.989 | D64: =D56+D57+D58+D59+D60+D61+D62+D63 -> 5442.737 | E64: =E56+E57+E58+E59+E60+E61+E62+E63 -> 5456.9574 | F64: =F56+F57+F58+F59+F60+F61+F62+F63 -> 5557.2457 | G64: =G56+G57+G58+G59+G60+G61+G62+G63 -> 5695.2144 | H64: =H56+H57+H58+H59+H60+H61+H62+H63 -> 5866.8117
A66: Cuentas por pagar | C66: =C22 -> 260.791 | D66: =D22 -> 335.42132 | E66: =E22 -> 382.3803 | F66: =F22 -> 430.17784 | G66: =G22 -> 473.19563 | H66: =H22 -> 506.31932
A67: Ingresos diferidos | C67: =C23 -> 143.445 | D67: =D23 -> 163.25425 | E67: =E23 -> 186.10984 | F67: =F23 -> 209.37357 | G67: =G23 -> 230.31093 | H67: =H23 -> 246.43269
A68: Pasivos acumulados | C68: =C24 -> 59.224 | D68: =D24 -> 64.60904 | E68: =E24 -> 73.654305 | F68: =F24 -> 82.861094 | G68: =G24 -> 91.147203 | H68: =H24 -> 97.527507
A69: Impuestos por pagar y otros pasivos corrientes (constantes) | C69: =Historicos!$E$55+Historicos!$E$60+Historicos!$E$56 -> 140.783 | D69: =C69 -> 140.783 | E69: =D69 -> 140.783 | F69: =E69 -> 140.783 | G69: =F69 -> 140.783 | H69: =G69 -> 140.783
A70: Línea de crédito (variable de cierre) | C70: 0 | D70: =MAX(0,-D84) -> 117.95609 | E70: =MAX(0,-E84) -> 195.68686 | F70: =MAX(0,-F84) -> 310.63694 | G70: =MAX(0,-G84) -> 429.84826 | H70: =MAX(0,-H84) -> 563.43349
A71: Deuda de adquisición (2012: saldo a refinanciar) | C71: =Deuda!$C$5 -> 3757.5455 | D71: =Deuda!L$12 -> 3467.6235 | E71: =Deuda!M$12 -> 3161.3477 | F71: =Deuda!N$12 -> 2837.7955 | G71: =Deuda!O$12 -> 2495.9924 | H71: =Deuda!P$12 -> 2134.909
A72: Impuestos diferidos, retiro de activos y otros pasivos LP (constantes) | C72: =Historicos!$E$65+Historicos!$E$66+Historicos!$E$67 -> 765.786 | D72: =C72 -> 765.786 | E72: =D72 -> 765.786 | F72: =E72 -> 765.786 | G72: =F72 -> 765.786 | H72: =G72 -> 765.786
A73: Interés minoritario (constante) | C73: =Historicos!$E$68 -> 43.396 | D73: =C73 -> 43.396 | E73: =D73 -> 43.396 | F73: =E73 -> 43.396 | G73: =F73 -> 43.396 | H73: =G73 -> 43.396
A74: Patrimonio | C74: =Historicos!$E$90-(Deuda!$C$5-Historicos!$E$62-Historicos!$E$57)-(Historicos!$E$35+Historicos!$E$36) -> 220.01855 | D74: =C74+D54 -> 343.90782 | E74: =D74+E54 -> 507.8134 | F74: =E74+F54 -> 736.43579 | G74: =F74+G54 -> 1024.7549 | H74: =G74+H54 -> 1368.2248
A75: Total pasivos y patrimonio | C75: =C66+C67+C68+C69+C70+C71+C72+C73+C74 -> 5390.989 | D75: =D66+D67+D68+D69+D70+D71+D72+D73+D74 -> 5442.737 | E75: =E66+E67+E68+E69+E70+E71+E72+E73+E74 -> 5456.9574 | F75: =F66+F67+F68+F69+F70+F71+F72+F73+F74 -> 5557.2457 | G75: =G66+G67+G68+G69+G70+G71+G72+G73+G74 -> 5695.2144 | H75: =H66+H67+H68+H69+H70+H71+H72+H73+H74 -> 5866.8117
A76: Control: activos − pasivos y patrimonio | C76: =C64-C75 -> 0 | D76: =D64-D75 -> 0 | E76: =E64-E75 -> 0 | F76: =F64-F75 -> 0 | G76: =G64-G75 -> 0 | H76: =H64-H75 -> 0 | I76: =MAX(ABS(C76),ABS(D76),ABS(E76),ABS(F76),ABS(G76),ABS(H76)) -> 0
A78: Flujo operativo = utilidad neta + D&A − Δ capital de trabajo | D78: =D54+D14-D26 -> 803.24033 | E78: =E54+E14-E26 -> 948.19795 | F78: =F54+F14-F26 -> 1076.0409 | G78: =G54+G14-G26 -> 1192.6774 | H78: =H54+H14-H26 -> 1282.5062
A79: Flujo de inversión = − capex | D79: =-D27 -> -631.27447 | E79: =-E27 -> -719.65289 | F79: =-F27 -> -867.43875 | G79: =-G27 -> -970.08567 | H79: =-H27 -> -1055.0079
A80: Amortización ordinaria de la deuda | D80: =Deuda!L$10 -> 289.92195 | E80: =Deuda!M$10 -> 306.27583 | F80: =Deuda!N$10 -> 323.55219 | G80: =Deuda!O$10 -> 341.80308 | H80: =Deuda!P$10 -> 361.08346
A81: Variación de la línea de crédito | D81: =D70-C70 -> 117.95609 | E81: =E70-D70 -> 77.730769 | F81: =F70-E70 -> 114.95009 | G81: =G70-F70 -> 119.21132 | H81: =H70-G70 -> 133.58522
A82: Variación de caja | D82: =D78+D79-D80+D81 -> 0 | E82: =E78+E79-E80+E81 -> 0 | F82: =F78+F79-F80+F81 -> 0 | G82: =G78+G79-G80+G81 -> 0 | H82: =H78+H79-H80+H81 -> 0
A83: Control: variación de caja del flujo − del balance | D83: =D82-(D56-C56) -> 0 | E83: =E82-(E56-D56) -> 0 | F83: =F82-(F56-E56) -> 0 | G83: =G82-(G56-F56) -> 0 | H83: =H82-(H56-G56) -> 0 | I83: =MAX(ABS(D83),ABS(E83),ABS(F83),ABS(G83),ABS(H83)) -> 0
A84: Caja disponible antes de línea de crédito (caja inicial − línea inicial + flujos − amortización) | D84: =C56-C70+D78+D79-D80 -> -117.95609 | E84: =D56-D70+E78+E79-E80 -> -195.68686 | F84: =E56-E70+F78+F79-F80 -> -310.63694 | G84: =F56-F70+G78+G79-G80 -> -429.84826 | H84: =G56-G70+H78+H79-H80 -> -563.43349
A86: Indicador: margen EBIT | C86: =C15/C8 -> 0.1142995 | D86: =D15/D8 -> 0.090020355 | E86: =E15/E8 -> 0.090020355 | F86: =F15/F8 -> 0.096421588 | G86: =G15/G8 -> 0.10142159 | H86: =H15/H8 -> 0.10642159
A87: Indicador: margen neto | D87: =D54/D8 -> 0.027475368 | E87: =E54/E8 -> 0.031885902 | F87: =F54/F8 -> 0.03953404 | G87: =G54/G8 -> 0.045324523 | H87: =H54/H8 -> 0.050462014
A88: Indicador: ROE (utilidad neta / patrimonio inicial) | D88: =D54/C74 -> 0.5630856 | E88: =E54/D74 -> 0.47659742 | F88: =F54/E74 -> 0.45020945 | G88: =G54/F74 -> 0.39150616 | H88: =H54/G74 -> 0.33517266
A89: Indicador: deuda total / EBITDA | C89: =(C71+C70)/C12 -> 3.6363636 | D89: =(D71+D70)/D12 -> 3.2269366 | E89: =(E71+E70)/E12 -> 2.6502206 | F89: =(F71+F70)/F12 -> 2.209368 | G89: =(G71+G70)/G12 -> 1.8665158 | H89: =(H71+H70)/H12 -> 1.6087712
A90: Indicador: EBITDA / intereses totales | D90: =D12/(D50+D51) -> 5.5716101 | E90: =E12/(E50+E51) -> 6.6822233 | F90: =F12/(F50+F51) -> 8.0710552 | G90: =G12/(G50+G51) -> 9.5214363 | H90: =H12/(H50+H51) -> 11.041268
A91: Indicador: deuda total / valor de las operaciones (solo 2007) | C91: =C71/Proyeccion!$H$41 -> 0.61562331

Sheet Sinergias
A1: Sinergias con American Cable (Tablas 4 y 5), millones de US$
C3: 2007 | D3: 2008 | E3: 2009 | F3: 2010 | G3: 2011 | H3: 2012 | I3: 2013
A4: Costos de operación del sistema (sin sinergias) | D4: =Proyeccion!D9 -> 838.86604 | E4: =Proyeccion!E9 -> 956.30728 | F4: =Proyeccion!F9 -> 1075.8457 | G4: =Proyeccion!G9 -> 1183.4303 | H4: =Proyeccion!H9 -> 1266.2704
A5: Backhaul / costos del sistema | D5: =Supuestos!D$55 -> 0.2 | E5: =Supuestos!E$55 -> 0.2 | F5: =Supuestos!F$55 -> 0.2 | G5: =Supuestos!G$55 -> 0.2 | H5: =Supuestos!H$55 -> 0.2
A6: Costo estimado de backhaul | D6: =D4*D5 -> 167.77321 | E6: =E4*E5 -> 191.26146 | F6: =F4*F5 -> 215.16914 | G6: =G4*G5 -> 236.68605 | H6: =H4*H5 -> 253.25408
A7: Reducción del costo de backhaul | D7: =Supuestos!D$56 -> 0 | E7: =Supuestos!E$56 -> 0.07 | F7: =Supuestos!F$56 -> 0.12 | G7: =Supuestos!G$56 -> 0.222 | H7: =Supuestos!H$56 -> 0.3
A8: Ahorro de backhaul (antes de impuestos) | D8: =D6*D7 -> 0 | E8: =E6*E7 -> 13.388302 | F8: =F6*F7 -> 25.820297 | G8: =G6*G7 -> 52.544304 | H8: =H6*H7 -> 75.976223
A10: Suscriptores empresariales promedio (millones) | D10: =Supuestos!D$57 -> 0.3 | E10: =Supuestos!E$57 -> 0.5 | F10: =Supuestos!F$57 -> 0.7 | G10: =Supuestos!G$57 -> 1 | H10: =Supuestos!H$57 -> 1.2
A11: Minutos mensuales por suscriptor | D11: =Supuestos!D$58 -> 859 | E11: =Supuestos!E$58 -> 885 | F11: =Supuestos!F$58 -> 911 | G11: =Supuestos!G$58 -> 939 | H11: =Supuestos!H$58 -> 967
A12: Minutos mensuales totales (millones) | D12: =D10*D11 -> 257.7 | E12: =E10*E11 -> 442.5 | F12: =F10*F11 -> 637.7 | G12: =G10*G11 -> 939 | H12: =H10*H11 -> 1160.4
A13: Ingreso por minuto (US$) | D13: =Supuestos!D$59 -> 0.0506 | E13: =Supuestos!E$59 -> 0.0506 | F13: =Supuestos!F$59 -> 0.0506 | G13: =Supuestos!G$59 -> 0.0506 | H13: =Supuestos!H$59 -> 0.0506
A14: Ingreso anual adicional por clientes empresariales | D14: =D12*D13*12 -> 156.47544 | E14: =E12*E13*12 -> 268.686 | F14: =F12*F13*12 -> 387.21144 | G14: =G12*G13*12 -> 570.1608 | H14: =H12*H13*12 -> 704.59488
A15: Margen EBITDA aplicado a los ingresos adicionales (selector) | D15: =IF(Supuestos!$C$28=1,Proyeccion!D13,1-Supuestos!D$37-Supuestos!D$39) -> 0.24642159 | E15: =IF(Supuestos!$C$28=1,Proyeccion!E13,1-Supuestos!E$37-Supuestos!E$39) -> 0.24642159 | F15: =IF(Supuestos!$C$28=1,Proyeccion!F13,1-Supuestos!F$37-Supuestos!F$39) -> 0.24642159 | G15: =IF(Supuestos!$C$28=1,Proyeccion!G13,1-Supuestos!G$37-Supuestos!G$39) -> 0.24642159 | H15: =IF(Supuestos!$C$28=1,Proyeccion!H13,1-Supuestos!H$37-Supuestos!H$39) -> 0.24642159
A16: EBITDA adicional por clientes empresariales | D16: =D14*D15 -> 38.558926 | E16: =E14*E15 -> 66.210031 | F16: =F14*F15 -> 95.417258 | G16: =G14*G15 -> 140.49993 | H16: =H14*H15 -> 173.62739
A18: Sinergias totales antes de impuestos | D18: =D8+D16 -> 38.558926 | E18: =E8+E16 -> 79.598333 | F18: =F8+F16 -> 121.23755 | G18: =G8+G16 -> 193.04423 | H18: =H8+H16 -> 249.60361
A19: Sinergias después de impuestos | D19: =D18*(1-Supuestos!$C$6) -> 23.135356 | E19: =E18*(1-Supuestos!$C$6) -> 47.759 | F19: =F18*(1-Supuestos!$C$6) -> 72.742533 | G19: =G18*(1-Supuestos!$C$6) -> 115.82654 | H19: =H18*(1-Supuestos!$C$6) -> 149.76217
A20: Sinergias después de impuestos × % realizado | D20: =D19*Supuestos!$C$30 -> 23.135356 | E20: =E19*Supuestos!$C$30 -> 47.759 | F20: =F19*Supuestos!$C$30 -> 72.742533 | G20: =G19*Supuestos!$C$30 -> 115.82654 | H20: =H19*Supuestos!$C$30 -> 149.76217
A22: Valoración (descontadas a Ku; perpetuidad desde 2013 creciendo a g, sin inversión adicional)
C23: Backhaul | D23: Ingresos | E23: Total
A24: VP de los flujos 2008-2012 | C24: =NPV(Costo_Capital!$C$10,D8:H8)*(1-Supuestos!$C$6)*Supuestos!$C$30 -> 72.740721 | D24: =NPV(Costo_Capital!$C$10,D16:H16)*(1-Supuestos!$C$6)*Supuestos!$C$30 -> 232.00833 | E24: =C24+D24 -> 304.74905
A25: VP del valor terminal | C25: =H8*(1-Supuestos!$C$6)*Supuestos!$C$30*(1+Proyeccion!$H$34)/(Costo_Capital!$C$10-Proyeccion!$H$34)/(1+Costo_Capital!$C$10)^5 -> 578.41339 | D25: =H16*(1-Supuestos!$C$6)*Supuestos!$C$30*(1+Proyeccion!$H$34)/(Costo_Capital!$C$10-Proyeccion!$H$34)/(1+Costo_Capital!$C$10)^5 -> 1321.84 | E25: =C25+D25 -> 1900.2534
A26: Valor presente de las sinergias | C26: =C24+C25 -> 651.15411 | D26: =D24+D25 -> 1553.8483 | E26: =E24+E25 -> 2205.0024
A27: Control: total = VP de la fila 'sinergias × % realizado' + valor terminal | E27: =E26-(NPV(Costo_Capital!$C$10,D20:H20)+H20*(1+Proyeccion!$H$34)/(Costo_Capital!$C$10-Proyeccion!$H$34)/(1+Costo_Capital!$C$10)^5) -> 0
A28: VP de las sinergias con 100% de realización (para sensibilidad) | E28: =NPV(Costo_Capital!$C$10,D19:H19)+H19*(1+Proyeccion!$H$34)/(Costo_Capital!$C$10-Proyeccion!$H$34)/(1+Costo_Capital!$C$10)^5 -> 2205.0024
A30: Supuestos propios: (1) el caso solo da ingresos empresariales, no su margen; base = margen EBITDA proyectado de ATC;
A31: (2) no se asume capex ni capital de trabajo adicional (el caso dice que el negocio empresarial usa capacidad ociosa de la red);
A32: (3) ambos tipos de sinergia se descuentan a Ku; las de ingresos son más inciertas, por eso se muestran por separado;
A33: (4) los costos de integración no aparecen en el caso y no se incluyen (sesgo al alza del valor de las sinergias).

Sheet Valoracion
A1: Valoración de AirThread: APV (método de American Cable) y contrastes (millones de US$)
A3: A. Valor de las operaciones (APV, sin sinergias)
A5: Costo de capital no apalancado (Ku) | C5: =Costo_Capital!$C$10 -> 0.082337439
A6: CPPC objetivo para el valor terminal | C6: =Costo_Capital!$C$16 -> 0.076150776
A7: Crecimiento a perpetuidad (g) | C7: =Proyeccion!$H$34 -> 0.027801065
A8: VP de los flujos libres 2008-2012 | C8: =Proyeccion!$H$38 -> 1258.417
A9: VP del valor terminal (perpetuidad) | C9: =Proyeccion!$H$39 -> 4560.4438
A10: VP de los escudos fiscales de la deuda de adquisición 2008-2012 | C10: =Proyeccion!$H$40 -> 284.78312
A11: Valor de las operaciones (APV) | C11: =Proyeccion!$H$41 -> 6103.6439
A12: Valor terminal / valor de las operaciones | C12: =C9/C11 -> 0.7471674
A14: B. Activos no operativos y otros derechos
A15: Caja y valores negociables 2007 | C15: =Historicos!$E$35+Historicos!$E$36 -> 220.885 | H15: Caso, p. 6: probablemente se usarán para financiar la compra. Se suma completa.
A16: Participación en utilidades de afiliadas 2007 | C16: =Historicos!$E$15 -> 90.033 | H16: Anexo 4.
A17: Valor de las afiliadas | C17: =IF(Supuestos!$C$27=1,C16*Supuestos!$C$15,Historicos!$E$47) -> 1719.1801 | H17: Base: P/U de la industria × utilidad (caso, nota 3). Alternativa: valor en libros (157,7).
A18: Nota por cobrar de largo plazo | C18: =Historicos!$E$48 -> 4.422 | H18: Anexo 5, a valor en libros.
A19: Títulos de renta variable negociables | C19: =Historicos!$E$46 -> 0 | H19: Anexo 5 (cero en 2007).
A20: Total activos no operativos | C20: =C15+C17+C18+C19 -> 1944.4871
A22: Deuda existente (largo plazo + pagaré), se refinancia | C22: =Historicos!$E$62+Historicos!$E$57 -> 1002.293 | H22: Anexo 5.
A23: Interés minoritario en resultados 2007 | C23: =Historicos!$E$21 -> 15.056 | H23: Anexo 4.
A24: Valor del interés minoritario | C24: =IF(Supuestos!$C$27=1,C23*Supuestos!$C$15,Historicos!$E$68) -> 287.49432 | H24: Coherente con afiliadas: P/U de la industria. Alternativa: libros (43,4).
A26: Total deuda e interés minoritario | C26: =C22+C24 -> 1289.7873
A28: C. Valor del patrimonio
A29: Valor de las operaciones (APV) | C29: =C11 -> 6103.6439
A30: + Activos no operativos | C30: =C20 -> 1944.4871
A31: Valor total de la empresa | C31: =C29+C30 -> 8048.131
A32: − Deuda existente e interés minoritario | C32: =C26 -> 1289.7873
A33: Valor del patrimonio, 100%, sin sinergias (valor intrínseco independiente) | C33: =C31-C32 -> 6758.3437
A34: Descuento por iliquidez aplicado | C34: =Supuestos!$C$29 -> 0
A35: Valor del patrimonio después del descuento | C35: =C33*(1-C34) -> 6758.3437
A36: + VP sinergias de backhaul | C36: =Sinergias!$C$26 -> 651.15411
A37: + VP sinergias de ingresos empresariales | C37: =Sinergias!$D$26 -> 1553.8483
A38: Valor del patrimonio con todas las sinergias | C38: =C35+C36+C37 -> 8963.3461
A39: Control: bloque de la hoja Proyeccion − fila 33 | C39: =Proyeccion!$H$44-C33 -> 0
A41: D. Contrastes
A42: Valor terminal por múltiplo VE/EBITDA de comparables (2012) | C42: =Proyeccion!$H$37 -> 17331.949
A43: Múltiplo VE/EBITDA usado | C43: =IF(Supuestos!$C$26=1,Comparables!$P$11,Comparables!$P$13) -> 10.333433
A44: Múltiplo VE/EBITDA 2012 implícito en el valor terminal por perpetuidad | C44: =Proyeccion!$H$36/Proyeccion!H12 -> 4.0384781
A45: Valor de las operaciones con valor terminal por múltiplo | C45: =C8+C10+C42/(1+C5)^5 -> 13212.21
A46: Patrimonio con valor terminal por múltiplo (sin sinergias) | C46: =C45+C30-C32 -> 13866.909
A47: Crecimiento implícito en el múltiplo (resuelve VT = NOPAT₂₀₁₂(1+g)(1−g/ROIC)/(CPPC−g)) | C47: =(-F47-SQRT(F47^2-4*E47*D47))/(2*E47) -> 0.066469351 | D47: =C42*C6-Proyeccion!$H$17 -> 885.22606 | E47: =Proyeccion!$H$17/Proyeccion!$H$30 -> 4171.4806 | F47: =-(C42+Proyeccion!$H$17-Proyeccion!$H$17/Proyeccion!$H$30) -> -13595.084 | H47: Celdas D-F: coeficientes c, a, b de la cuadrática.
A48: CPPC-DCF a estructura objetivo constante: valor de las operaciones | C48: =NPV(C6,Proyeccion!D28:H28)+Proyeccion!H36/(1+C6)^5 -> 5972.3549
A49: Patrimonio por CPPC-DCF (sin sinergias) | C49: =C48+C30-C32 -> 6627.0547
A50: Diferencia APV − CPPC-DCF (valor del endeudamiento inicial por encima del objetivo, neto) | C50: =C33-C49 -> 131.28901
A51: VE/EBITDA 2007 implícito en el valor de las operaciones | C51: =C11/Historicos!$E$11 -> 5.9067998
A52: VE/EBITDA 2008 implícito en el valor de las operaciones | C52: =C11/Proyeccion!D12 -> 5.4931347
A53: Valor del patrimonio por múltiplo VE/EBITDA 2007 actual (mediana) | C53: =Historicos!$E$11*Comparables!$P$13+C30-C32 -> 11332.494
A54: Valor del patrimonio por P/U de la industria × utilidad neta 2007 | C54: =Historicos!$E$22*Supuestos!$C$15 -> 6009.8457
A55: Deuda de adquisición / valor de las operaciones (límite 50%) | C55: =Deuda!$C$5/C11 -> 0.61562331
A56: Deuda de adquisición / valor total de la empresa con activos no operativos | C56: =Deuda!$C$5/C31 -> 0.46688423
A57: E. Rango de precio para la negociación (patrimonio 100%, millones de US$)
A58: Apertura: valor independiente con el descuento por iliquidez de una salida a bolsa (10%, nota 6) | C58: =C33*(1-Supuestos!$C$16) -> 6082.5093 | H58: Costo de salir a bolsa: 10% (nota 6 del caso).
A59: Objetivo: valor independiente + 50% de las sinergias de backhaul | C59: =C33+Supuestos!$C$31*C36 -> 7083.9208 | H59: Comparte con el vendedor la mitad de la sinergia más cierta.
A60: Precio máximo (retiro): valor independiente + 100% backhaul (sin pagar sinergias de ingresos) | C60: =C33+C36 -> 7409.4978 | H60: Por encima, ACC transfiere al vendedor sinergias que solo ACC crea y que son inciertas.
A61: Referencia: valor con todas las sinergias (no pagar) | C61: =C33+C36+C37 -> 8963.3461
A63: Rendimiento anual exigido sobre el valor de las operaciones = Ku × valor (APV) | C63: =C5*C11 -> 502.55841
A64: Afiliadas / valor del patrimonio sin sinergias | C64: =C17/C33 -> 0.25437891
A65: Sinergias de ingresos / total de sinergias | C65: =C37/(C36+C37) -> 0.70469233
A66: Prima del precio máximo sobre el valor independiente | C66: =C60/C33-1 -> 0.09634818
A67: VE/EBITDA 2007 implícito en el precio máximo (con deuda existente y minoritario) | C67: =(C60+C32-C30)/Historicos!$E$11 -> 6.536954

Sheet Escenarios
A1: Escenarios de riesgo: el mismo bloque de cálculo con ajustes (millones de US$)
A3: Escenario: Base
A4: Año | C4: 2007 real | D4: 2008 | E4: 2009 | F4: 2010 | G4: 2011 | H4: 2012 | I4: 2013 normal.
A5: Ingresos por servicios | C5: =Historicos!$E$5 -> 3679.237 | D5: =C5*(1+D6) -> 4194.3302 | E5: =D5*(1+E6) -> 4781.5364 | F5: =E5*(1+F6) -> 5379.2285 | G5: =F5*(1+G6) -> 5917.1513 | H5: =G5*(1+H6) -> 6331.3519
A6: Crecimiento de ingresos por servicios | C6: =Historicos!$E$103 -> 0.14460725 | D6: =Supuestos!D$36+Supuestos!$C$63 -> 0.14 | E6: =Supuestos!E$36+Supuestos!$C$63 -> 0.14 | F6: =Supuestos!F$36+Supuestos!$C$63 -> 0.125 | G6: =Supuestos!G$36+Supuestos!$C$63 -> 0.1 | H6: =Supuestos!H$36+Supuestos!$C$63 -> 0.07
A7: Ingresos por equipos | C7: =Historicos!$E$6 -> 267.027 | D7: =D5*Supuestos!$C$45 -> 314.77315 | E7: =E5*Supuestos!$C$45 -> 358.84139 | F7: =F5*Supuestos!$C$45 -> 403.69657 | G7: =G5*Supuestos!$C$45 -> 444.06622 | H7: =H5*Supuestos!$C$45 -> 475.15086
A8: Ingresos totales | C8: =Historicos!$E$7 -> 3946.264 | D8: =D5+D7 -> 4509.1033 | E8: =E5+E7 -> 5140.3778 | F8: =F5+F7 -> 5782.925 | G8: =G5+G7 -> 6361.2175 | H8: =H5+H7 -> 6806.5027
A9: Costos de operación del sistema | C9: =Historicos!$E$8 -> 717.075 | D9: =D5*Supuestos!D$37 -> 838.86604 | E9: =E5*Supuestos!E$37 -> 956.30728 | F9: =F5*Supuestos!F$37 -> 1075.8457 | G9: =G5*Supuestos!G$37 -> 1183.4303 | H9: =H5*Supuestos!H$37 -> 1266.2704
A10: Costo de equipos vendidos | C10: =Historicos!$E$9 -> 640.225 | D10: =D7*Supuestos!D$38 -> 755.45556 | E10: =E7*Supuestos!E$38 -> 861.21934 | F10: =F7*Supuestos!F$38 -> 968.87176 | G10: =G7*Supuestos!G$38 -> 1065.7589 | H10: =H7*Supuestos!H$38 -> 1140.3621
A11: SG&A | C11: =Historicos!$E$10 -> 1555.639 | D11: =D8*(Supuestos!D$39+Supuestos!$C$64) -> 1803.6413 | E11: =E8*(Supuestos!E$39+Supuestos!$C$64) -> 2056.1511 | F11: =F8*(Supuestos!F$39+Supuestos!$C$64) -> 2313.17 | G11: =G8*(Supuestos!G$39+Supuestos!$C$64) -> 2544.487 | H11: =H8*(Supuestos!H$39+Supuestos!$C$64) -> 2722.6011
A12: EBITDA | C12: =Historicos!$E$11 -> 1033.325 | D12: =D8-D9-D10-D11 -> 1111.1404 | E12: =E8-E9-E10-E11 -> 1266.7001 | F12: =F8-F9-F10-F11 -> 1425.0376 | G12: =G8-G9-G10-G11 -> 1567.5413 | H12: =H8-H9-H10-H11 -> 1677.2692
A13: Margen EBITDA | C13: =C12/C8 -> 0.26184893 | D13: =D12/D8 -> 0.24642159 | E13: =E12/E8 -> 0.24642159 | F13: =F12/F8 -> 0.24642159 | G13: =G12/G8 -> 0.24642159 | H13: =H12/H8 -> 0.24642159
A14: Depreciación y amortización | C14: =Historicos!$E$12 -> 582.269 | D14: =D8*Supuestos!D$42 -> 705.22932 | E14: =E8*Supuestos!E$42 -> 803.96142 | F14: =F8*Supuestos!F$42 -> 867.43875 | G14: =G8*Supuestos!G$42 -> 922.37654 | H14: =H8*Supuestos!H$42 -> 952.91038
A15: EBIT | C15: =Historicos!$E$13 -> 451.056 | D15: =D12-D14 -> 405.91108 | E15: =E12-E14 -> 462.73863 | F15: =F12-F14 -> 557.59881 | G15: =G12-G14 -> 645.16478 | H15: =H12-H14 -> 724.35883
A16: Impuestos operativos (EBIT × t) | D16: =D15*Supuestos!$C$6 -> 162.36443 | E16: =E15*Supuestos!$C$6 -> 185.09545 | F16: =F15*Supuestos!$C$6 -> 223.03952 | G16: =G15*Supuestos!$C$6 -> 258.06591 | H16: =H15*Supuestos!$C$6 -> 289.74353
A17: Utilidad operativa después de impuestos (NOPAT) | D17: =D15-D16 -> 243.54665 | E17: =E15-E16 -> 277.64318 | F17: =F15-F16 -> 334.55929 | G17: =G15-G16 -> 387.09887 | H17: =H15-H16 -> 434.6153 | I17: =H17*(1+H34) -> 446.69807
A18: Costos operativos en efectivo | C18: =C9+C10+C11 -> 2912.939 | D18: =D9+D10+D11 -> 3397.9629 | E18: =E9+E10+E11 -> 3873.6777 | F18: =F9+F10+F11 -> 4357.8875 | G18: =G9+G10+G11 -> 4793.6762 | H18: =H9+H10+H11 -> 5129.2335
A19: Cuentas por cobrar | C19: =Historicos!$E$37 -> 435.497 | D19: =D8*Supuestos!$C$46/360 -> 521.89513 | E19: =E8*Supuestos!$C$46/360 -> 594.96044 | F19: =F8*Supuestos!$C$46/360 -> 669.3305 | G19: =G8*Supuestos!$C$46/360 -> 736.26355 | H19: =H8*Supuestos!$C$46/360 -> 787.802
A20: Inventario | C20: =Historicos!$E$38 -> 100.99 | D20: =D7*Supuestos!$C$47/360 -> 134.96792 | E20: =E7*Supuestos!$C$47/360 -> 153.86343 | F20: =F7*Supuestos!$C$47/360 -> 173.09635 | G20: =G7*Supuestos!$C$47/360 -> 190.40599 | H20: =H7*Supuestos!$C$47/360 -> 203.73441
A21: Gastos prepagados | C21: =Historicos!$E$39 -> 41.588 | D21: =D18*Supuestos!$C$48 -> 46.914828 | E21: =E18*Supuestos!$C$48 -> 53.482904 | F21: =F18*Supuestos!$C$48 -> 60.168267 | G21: =G18*Supuestos!$C$48 -> 66.185093 | H21: =H18*Supuestos!$C$48 -> 70.81805
A22: Cuentas por pagar | C22: =Historicos!$E$52 -> 260.791 | D22: =D18*Supuestos!$C$49/360 -> 335.42132 | E22: =E18*Supuestos!$C$49/360 -> 382.3803 | F22: =F18*Supuestos!$C$49/360 -> 430.17784 | G22: =G18*Supuestos!$C$49/360 -> 473.19563 | H22: =H18*Supuestos!$C$49/360 -> 506.31932
A23: Ingresos diferidos | C23: =Historicos!$E$53 -> 143.445 | D23: =D5*Supuestos!$C$50/360 -> 163.25425 | E23: =E5*Supuestos!$C$50/360 -> 186.10984 | F23: =F5*Supuestos!$C$50/360 -> 209.37357 | G23: =G5*Supuestos!$C$50/360 -> 230.31093 | H23: =H5*Supuestos!$C$50/360 -> 246.43269
A24: Pasivos acumulados | C24: =Historicos!$E$54 -> 59.224 | D24: =D18*Supuestos!$C$51/360 -> 64.60904 | E24: =E18*Supuestos!$C$51/360 -> 73.654305 | F24: =F18*Supuestos!$C$51/360 -> 82.861094 | G24: =G18*Supuestos!$C$51/360 -> 91.147203 | H24: =H18*Supuestos!$C$51/360 -> 97.527507
A25: Capital de trabajo operativo neto | C25: =C19+C20+C21-C22-C23-C24 -> 114.615 | D25: =D19+D20+D21-D22-D23-D24 -> 140.49327 | E25: =E19+E20+E21-E22-E23-E24 -> 160.16232 | F25: =F19+F20+F21-F22-F23-F24 -> 180.18261 | G25: =G19+G20+G21-G22-G23-G24 -> 198.20087 | H25: =H19+H20+H21-H22-H23-H24 -> 212.07494
A26: Aumento del capital de trabajo operativo neto | D26: =D25-C25 -> 25.878265 | E26: =E25-D25 -> 19.669057 | F26: =F25-E25 -> 20.02029 | G26: =G25-F25 -> 18.018261 | H26: =H25-G25 -> 13.874061
A27: Capex | D27: =D8*(Supuestos!D$41+Supuestos!$C$65) -> 631.27447 | E27: =E8*(Supuestos!E$41+Supuestos!$C$65) -> 719.65289 | F27: =F8*(Supuestos!F$41+Supuestos!$C$65) -> 867.43875 | G27: =G8*(Supuestos!G$41+Supuestos!$C$65) -> 970.08567 | H27: =H8*(Supuestos!H$41+Supuestos!$C$65) -> 1055.0079
A28: Flujo de caja libre no apalancado | D28: =D17+D14-D27-D26 -> 291.62324 | E28: =E17+E14-E27-E26 -> 342.28266 | F28: =F17+F14-F27-F26 -> 314.539 | G28: =G17+G14-G27-G26 -> 321.37148 | H28: =H17+H14-H27-H26 -> 318.6437 | I28: =I17*(1-H35) -> 327.50233
A29: Capital invertido contable (patrimonio + deuda) | C29: =Historicos!$E$90+Historicos!$E$62+Historicos!$E$57 -> 4198.449 | D29: =C29+D27-D14+D26 -> 4150.3724 | E29: =D29+E27-E14+E26 -> 4085.7329 | F29: =E29+F27-F14+F26 -> 4105.7532 | G29: =F29+G27-G14+G26 -> 4171.4806 | H29: =G29+H27-H14+H26 -> 4287.4522
A30: ROIC (NOPAT / capital invertido al inicio del año) | D30: =D17/C29 -> 0.058008719 | E30: =E17/D29 -> 0.066895968 | F30: =F17/E29 -> 0.081884766 | G30: =G17/F29 -> 0.094282059 | H30: =H17/G29 -> 0.1041873
A31: Tasa de reinversión = (capex − D&A + Δ capital de trabajo) / NOPAT | D31: =(D27-D14+D26)/D17 -> -0.19740197 | E31: =(E27-E14+E26)/E17 -> -0.23281492 | F31: =(F27-F14+F26)/F17 -> 0.059840785 | G31: =(G27-G14+G26)/G17 -> 0.16979485 | H31: =(H27-H14+H26)/H17 -> 0.26683737
A33: Crecimiento fundamental = ROIC 2012 × tasa de reinversión 2012 | H33: =H30*H31 -> 0.027801065
A34: Crecimiento a perpetuidad usado (g) | H34: =IF(Supuestos!$C$24=1,H33,Supuestos!$C$25) -> 0.027801065
A35: Tasa de reinversión de largo plazo = g / ROIC 2012 | H35: =H34/H30 -> 0.26683737
A36: Valor terminal 2012 = FCF 2013 / (CPPC − g) | H36: =I28/(Costo_Capital!$C$16-H34) -> 6773.615
A37: Valor terminal 2012 por múltiplo VE/EBITDA (contraste) | H37: =H12*IF(Supuestos!$C$26=1,Comparables!$P$11,Comparables!$P$13) -> 17331.949
A38: VP de los FCF 2008-2012 a Ku | H38: =NPV(Costo_Capital!$C$10,D28:H28) -> 1258.417
A39: VP del valor terminal a Ku | H39: =H36/(1+Costo_Capital!$C$10)^5 -> 4560.4438
A40: VP de los escudos fiscales 2008-2012 a Kd | H40: =NPV(Supuestos!$C$7,Deuda!$L$13:$P$13) -> 284.78312
A41: Valor de las operaciones (APV) | H41: =H38+H39+H40 -> 6103.6439
A42: + Activos no operativos | H42: =Valoracion!$C$20 -> 1944.4871
A43: − Deuda existente e interés minoritario | H43: =Valoracion!$C$26 -> 1289.7873
A44: Valor del patrimonio (100%, antes de descuento por iliquidez) | H44: =H41+H42-H43 -> 6758.3437
A47: Escenario: Precios
A48: Año | C48: 2007 real | D48: 2008 | E48: 2009 | F48: 2010 | G48: 2011 | H48: 2012 | I48: 2013 normal.
A49: Ingresos por servicios | C49: =Historicos!$E$5 -> 3679.237 | D49: =C49*(1+D50) -> 4083.9531 | E49: =D49*(1+E50) -> 4533.1879 | F49: =E49*(1+F50) -> 4963.8408 | G49: =F49*(1+G50) -> 5311.3096 | H49: =G49*(1+H50) -> 5523.762
A50: Crecimiento de ingresos por servicios | C50: =Historicos!$E$103 -> 0.14460725 | D50: =Supuestos!D$36+Supuestos!$D$63 -> 0.11 | E50: =Supuestos!E$36+Supuestos!$D$63 -> 0.11 | F50: =Supuestos!F$36+Supuestos!$D$63 -> 0.095 | G50: =Supuestos!G$36+Supuestos!$D$63 -> 0.07 | H50: =Supuestos!H$36+Supuestos!$D$63 -> 0.04
A51: Ingresos por equipos | C51: =Historicos!$E$6 -> 267.027 | D51: =D49*Supuestos!$C$45 -> 306.48965 | E51: =E49*Supuestos!$C$45 -> 340.20351 | F51: =F49*Supuestos!$C$45 -> 372.52284 | G51: =G49*Supuestos!$C$45 -> 398.59944 | H51: =H49*Supuestos!$C$45 -> 414.54342
A52: Ingresos totales | C52: =Historicos!$E$7 -> 3946.264 | D52: =D49+D51 -> 4390.4427 | E52: =E49+E51 -> 4873.3914 | F52: =F49+F51 -> 5336.3636 | G52: =G49+G51 -> 5709.9091 | H52: =H49+H51 -> 5938.3054
A53: Costos de operación del sistema | C53: =Historicos!$E$8 -> 717.075 | D53: =D49*Supuestos!D$37 -> 816.79061 | E53: =E49*Supuestos!E$37 -> 906.63758 | F53: =F49*Supuestos!F$37 -> 992.76815 | G53: =G49*Supuestos!G$37 -> 1062.2619 | H53: =H49*Supuestos!H$37 -> 1104.7524
A54: Costo de equipos vendidos | C54: =Historicos!$E$9 -> 640.225 | D54: =D51*Supuestos!D$38 -> 735.57515 | E54: =E51*Supuestos!E$38 -> 816.48842 | F54: =F51*Supuestos!F$38 -> 894.05482 | G54: =G51*Supuestos!G$38 -> 956.63865 | H54: =H51*Supuestos!H$38 -> 994.9042
A55: SG&A | C55: =Historicos!$E$10 -> 1555.639 | D55: =D52*(Supuestos!D$39+Supuestos!$D$64) -> 1756.1771 | E55: =E52*(Supuestos!E$39+Supuestos!$D$64) -> 1949.3566 | F55: =F52*(Supuestos!F$39+Supuestos!$D$64) -> 2134.5454 | G55: =G52*(Supuestos!G$39+Supuestos!$D$64) -> 2283.9636 | H55: =H52*(Supuestos!H$39+Supuestos!$D$64) -> 2375.3222
A56: EBITDA | C56: =Historicos!$E$11 -> 1033.325 | D56: =D52-D53-D54-D55 -> 1081.8999 | E56: =E52-E53-E54-E55 -> 1200.9088 | F56: =F52-F53-F54-F55 -> 1314.9952 | G56: =G52-G53-G54-G55 -> 1407.0449 | H56: =H52-H53-H54-H55 -> 1463.3266
A57: Margen EBITDA | C57: =C56/C52 -> 0.26184893 | D57: =D56/D52 -> 0.24642159 | E57: =E56/E52 -> 0.24642159 | F57: =F56/F52 -> 0.24642159 | G57: =G56/G52 -> 0.24642159 | H57: =H56/H52 -> 0.24642159
A58: Depreciación y amortización | C58: =Historicos!$E$12 -> 582.269 | D58: =D52*Supuestos!D$42 -> 686.67065 | E58: =E52*Supuestos!E$42 -> 762.20443 | F58: =F52*Supuestos!F$42 -> 800.45454 | G58: =G52*Supuestos!G$42 -> 827.93681 | H58: =H52*Supuestos!H$42 -> 831.36276
A59: EBIT | C59: =Historicos!$E$13 -> 451.056 | D59: =D56-D58 -> 395.22921 | E59: =E56-E58 -> 438.70442 | F59: =F56-F58 -> 514.54065 | G59: =G56-G58 -> 579.10804 | H59: =H56-H58 -> 631.96389
A60: Impuestos operativos (EBIT × t) | D60: =D59*Supuestos!$C$6 -> 158.09168 | E60: =E59*Supuestos!$C$6 -> 175.48177 | F60: =F59*Supuestos!$C$6 -> 205.81626 | G60: =G59*Supuestos!$C$6 -> 231.64322 | H60: =H59*Supuestos!$C$6 -> 252.78556
A61: Utilidad operativa después de impuestos (NOPAT) | D61: =D59-D60 -> 237.13753 | E61: =E59-E60 -> 263.22265 | F61: =F59-F60 -> 308.72439 | G61: =G59-G60 -> 347.46482 | H61: =H59-H60 -> 379.17833 | I61: =H61*(1+H78) -> 387.96157
A62: Costos operativos en efectivo | C62: =C53+C54+C55 -> 2912.939 | D62: =D53+D54+D55 -> 3308.5429 | E62: =E53+E54+E55 -> 3672.4826 | F62: =F53+F54+F55 -> 4021.3684 | G62: =G53+G54+G55 -> 4302.8642 | H62: =H53+H54+H55 -> 4474.9788
A63: Cuentas por cobrar | C63: =Historicos!$E$37 -> 435.497 | D63: =D52*Supuestos!$C$46/360 -> 508.16104 | E63: =E52*Supuestos!$C$46/360 -> 564.05876 | F63: =F52*Supuestos!$C$46/360 -> 617.64434 | G63: =G52*Supuestos!$C$46/360 -> 660.87944 | H63: =H52*Supuestos!$C$46/360 -> 687.31462
A64: Inventario | C64: =Historicos!$E$38 -> 100.99 | D64: =D51*Supuestos!$C$47/360 -> 131.41613 | E64: =E51*Supuestos!$C$47/360 -> 145.8719 | F64: =F51*Supuestos!$C$47/360 -> 159.72974 | G64: =G51*Supuestos!$C$47/360 -> 170.91082 | H64: =H51*Supuestos!$C$47/360 -> 177.74725
A65: Gastos prepagados | C65: =Historicos!$E$39 -> 41.588 | D65: =D62*Supuestos!$C$48 -> 45.680227 | E65: =E62*Supuestos!$C$48 -> 50.705052 | F65: =F62*Supuestos!$C$48 -> 55.522032 | G65: =G62*Supuestos!$C$48 -> 59.408574 | H65: =H62*Supuestos!$C$48 -> 61.784917
A66: Cuentas por pagar | C66: =Historicos!$E$52 -> 260.791 | D66: =D62*Supuestos!$C$49/360 -> 326.59444 | E66: =E62*Supuestos!$C$49/360 -> 362.51983 | F66: =F62*Supuestos!$C$49/360 -> 396.95922 | G66: =G62*Supuestos!$C$49/360 -> 424.74636 | H66: =H62*Supuestos!$C$49/360 -> 441.73621
A67: Ingresos diferidos | C67: =Historicos!$E$53 -> 143.445 | D67: =D49*Supuestos!$C$50/360 -> 158.95808 | E67: =E49*Supuestos!$C$50/360 -> 176.44347 | F67: =F49*Supuestos!$C$50/360 -> 193.2056 | G67: =G49*Supuestos!$C$50/360 -> 206.72999 | H67: =H49*Supuestos!$C$50/360 -> 214.99919
A68: Pasivos acumulados | C68: =Historicos!$E$54 -> 59.224 | D68: =D62*Supuestos!$C$51/360 -> 62.908802 | E68: =E62*Supuestos!$C$51/360 -> 69.82877 | F68: =F62*Supuestos!$C$51/360 -> 76.462503 | G68: =G62*Supuestos!$C$51/360 -> 81.814879 | H68: =H62*Supuestos!$C$51/360 -> 85.087474
A69: Capital de trabajo operativo neto | C69: =C63+C64+C65-C66-C67-C68 -> 114.615 | D69: =D63+D64+D65-D66-D67-D68 -> 136.79607 | E69: =E63+E64+E65-E66-E67-E68 -> 151.84364 | F69: =F63+F64+F65-F66-F67-F68 -> 166.26879 | G69: =G63+G64+G65-G66-G67-G68 -> 177.9076 | H69: =H63+H64+H65-H66-H67-H68 -> 185.02391
A70: Aumento del capital de trabajo operativo neto | D70: =D69-C69 -> 22.181074 | E70: =E69-D69 -> 15.047568 | F70: =F69-E69 -> 14.425146 | G70: =G69-F69 -> 11.638815 | H70: =H69-G69 -> 7.1163041
A71: Capex | D71: =D52*(Supuestos!D$41+Supuestos!$D$65) -> 614.66198 | E71: =E52*(Supuestos!E$41+Supuestos!$D$65) -> 682.2748 | F71: =F52*(Supuestos!F$41+Supuestos!$D$65) -> 800.45454 | G71: =G52*(Supuestos!G$41+Supuestos!$D$65) -> 870.76113 | H71: =H52*(Supuestos!H$41+Supuestos!$D$65) -> 920.43734
A72: Flujo de caja libre no apalancado | D72: =D61+D58-D71-D70 -> 286.96513 | E72: =E61+E58-E71-E70 -> 328.10471 | F72: =F61+F58-F71-F70 -> 294.29924 | G72: =G61+G58-G71-G70 -> 293.00169 | H72: =H61+H58-H71-H70 -> 282.98745 | I72: =I61*(1-H79) -> 289.54253
A73: Capital invertido contable (patrimonio + deuda) | C73: =Historicos!$E$90+Historicos!$E$62+Historicos!$E$57 -> 4198.449 | D73: =C73+D71-D58+D70 -> 4148.6214 | E73: =D73+E71-E58+E70 -> 4083.7393 | F73: =E73+F71-F58+F70 -> 4098.1645 | G73: =F73+G71-G58+G70 -> 4152.6276 | H73: =G73+H71-H58+H70 -> 4248.8185
A74: ROIC (NOPAT / capital invertido al inicio del año) | D74: =D61/C73 -> 0.056482174 | E74: =E61/D73 -> 0.063448223 | F74: =F61/E73 -> 0.075598456 | G74: =G61/F73 -> 0.084785476 | H74: =H61/G73 -> 0.091310459
A75: Tasa de reinversión = (capex − D&A + Δ capital de trabajo) / NOPAT | D75: =(D71-D58+D70)/D61 -> -0.2101211 | E75: =(E71-E58+E70)/E61 -> -0.24649117 | F75: =(F71-F58+F70)/F61 -> 0.046724996 | G75: =(G71-G58+G70)/G61 -> 0.15674431 | H75: =(H71-H58+H70)/H61 -> 0.25368244
A77: Crecimiento fundamental = ROIC 2012 × tasa de reinversión 2012 | H77: =H74*H75 -> 0.02316386
A78: Crecimiento a perpetuidad usado (g) | H78: =IF(Supuestos!$C$24=1,H77,Supuestos!$C$25) -> 0.02316386
A79: Tasa de reinversión de largo plazo = g / ROIC 2012 | H79: =H78/H74 -> 0.25368244
A80: Valor terminal 2012 = FCF 2013 / (CPPC − g) | H80: =I72/(Costo_Capital!$C$16-H78) -> 5464.4157
A81: Valor terminal 2012 por múltiplo VE/EBITDA (contraste) | H81: =H56*IF(Supuestos!$C$26=1,Comparables!$P$11,Comparables!$P$13) -> 15121.188
A82: VP de los FCF 2008-2012 a Ku | H82: =NPV(Costo_Capital!$C$10,D72:H72) -> 1181.3681
A83: VP del valor terminal a Ku | H83: =H80/(1+Costo_Capital!$C$10)^5 -> 3679.0045
A84: VP de los escudos fiscales 2008-2012 a Kd | H84: =NPV(Supuestos!$C$7,Deuda!$L$13:$P$13) -> 284.78312
A85: Valor de las operaciones (APV) | H85: =H82+H83+H84 -> 5145.1557
A86: + Activos no operativos | H86: =Valoracion!$C$20 -> 1944.4871
A87: − Deuda existente e interés minoritario | H87: =Valoracion!$C$26 -> 1289.7873
A88: Valor del patrimonio (100%, antes de descuento por iliquidez) | H88: =H85+H86-H87 -> 5799.8555
A91: Escenario: Adquisición
A92: Año | C92: 2007 real | D92: 2008 | E92: 2009 | F92: 2010 | G92: 2011 | H92: 2012 | I92: 2013 normal.
A93: Ingresos por servicios | C93: =Historicos!$E$5 -> 3679.237 | D93: =C93*(1+D94) -> 4194.3302 | E93: =D93*(1+E94) -> 4781.5364 | F93: =E93*(1+F94) -> 5379.2285 | G93: =F93*(1+G94) -> 5917.1513 | H93: =G93*(1+H94) -> 6331.3519
A94: Crecimiento de ingresos por servicios | C94: =Historicos!$E$103 -> 0.14460725 | D94: =Supuestos!D$36+Supuestos!$E$63 -> 0.14 | E94: =Supuestos!E$36+Supuestos!$E$63 -> 0.14 | F94: =Supuestos!F$36+Supuestos!$E$63 -> 0.125 | G94: =Supuestos!G$36+Supuestos!$E$63 -> 0.1 | H94: =Supuestos!H$36+Supuestos!$E$63 -> 0.07
A95: Ingresos por equipos | C95: =Historicos!$E$6 -> 267.027 | D95: =D93*Supuestos!$C$45 -> 314.77315 | E95: =E93*Supuestos!$C$45 -> 358.84139 | F95: =F93*Supuestos!$C$45 -> 403.69657 | G95: =G93*Supuestos!$C$45 -> 444.06622 | H95: =H93*Supuestos!$C$45 -> 475.15086
A96: Ingresos totales | C96: =Historicos!$E$7 -> 3946.264 | D96: =D93+D95 -> 4509.1033 | E96: =E93+E95 -> 5140.3778 | F96: =F93+F95 -> 5782.925 | G96: =G93+G95 -> 6361.2175 | H96: =H93+H95 -> 6806.5027
A97: Costos de operación del sistema | C97: =Historicos!$E$8 -> 717.075 | D97: =D93*Supuestos!D$37 -> 838.86604 | E97: =E93*Supuestos!E$37 -> 956.30728 | F97: =F93*Supuestos!F$37 -> 1075.8457 | G97: =G93*Supuestos!G$37 -> 1183.4303 | H97: =H93*Supuestos!H$37 -> 1266.2704
A98: Costo de equipos vendidos | C98: =Historicos!$E$9 -> 640.225 | D98: =D95*Supuestos!D$38 -> 755.45556 | E98: =E95*Supuestos!E$38 -> 861.21934 | F98: =F95*Supuestos!F$38 -> 968.87176 | G98: =G95*Supuestos!G$38 -> 1065.7589 | H98: =H95*Supuestos!H$38 -> 1140.3621
A99: SG&A | C99: =Historicos!$E$10 -> 1555.639 | D99: =D96*(Supuestos!D$39+Supuestos!$E$64) -> 1893.8234 | E99: =E96*(Supuestos!E$39+Supuestos!$E$64) -> 2158.9587 | F99: =F96*(Supuestos!F$39+Supuestos!$E$64) -> 2428.8285 | G99: =G96*(Supuestos!G$39+Supuestos!$E$64) -> 2671.7114 | H99: =H96*(Supuestos!H$39+Supuestos!$E$64) -> 2858.7312
A100: EBITDA | C100: =Historicos!$E$11 -> 1033.325 | D100: =D96-D97-D98-D99 -> 1020.9583 | E100: =E96-E97-E98-E99 -> 1163.8925 | F100: =F96-F97-F98-F99 -> 1309.3791 | G100: =G96-G97-G98-G99 -> 1440.317 | H100: =H96-H97-H98-H99 -> 1541.1392
A101: Margen EBITDA | C101: =C100/C96 -> 0.26184893 | D101: =D100/D96 -> 0.22642159 | E101: =E100/E96 -> 0.22642159 | F101: =F100/F96 -> 0.22642159 | G101: =G100/G96 -> 0.22642159 | H101: =H100/H96 -> 0.22642159
A102: Depreciación y amortización | C102: =Historicos!$E$12 -> 582.269 | D102: =D96*Supuestos!D$42 -> 705.22932 | E102: =E96*Supuestos!E$42 -> 803.96142 | F102: =F96*Supuestos!F$42 -> 867.43875 | G102: =G96*Supuestos!G$42 -> 922.37654 | H102: =H96*Supuestos!H$42 -> 952.91038
A103: EBIT | C103: =Historicos!$E$13 -> 451.056 | D103: =D100-D102 -> 315.72902 | E103: =E100-E102 -> 359.93108 | F103: =F100-F102 -> 441.94031 | G103: =G100-G102 -> 517.94043 | H103: =H100-H102 -> 588.22877
A104: Impuestos operativos (EBIT × t) | D104: =D103*Supuestos!$C$6 -> 126.29161 | E104: =E103*Supuestos!$C$6 -> 143.97243 | F104: =F103*Supuestos!$C$6 -> 176.77612 | G104: =G103*Supuestos!$C$6 -> 207.17617 | H104: =H103*Supuestos!$C$6 -> 235.29151
A105: Utilidad operativa después de impuestos (NOPAT) | D105: =D103-D104 -> 189.43741 | E105: =E103-E104 -> 215.95865 | F105: =F103-F104 -> 265.16419 | G105: =G103-G104 -> 310.76426 | H105: =H103-H104 -> 352.93726 | I105: =H105*(1+H122) -> 362.70194
A106: Costos operativos en efectivo | C106: =C97+C98+C99 -> 2912.939 | D106: =D97+D98+D99 -> 3488.145 | E106: =E97+E98+E99 -> 3976.4853 | F106: =F97+F98+F99 -> 4473.546 | G106: =G97+G98+G99 -> 4920.9006 | H106: =H97+H98+H99 -> 5265.3636
A107: Cuentas por cobrar | C107: =Historicos!$E$37 -> 435.497 | D107: =D96*Supuestos!$C$46/360 -> 521.89513 | E107: =E96*Supuestos!$C$46/360 -> 594.96044 | F107: =F96*Supuestos!$C$46/360 -> 669.3305 | G107: =G96*Supuestos!$C$46/360 -> 736.26355 | H107: =H96*Supuestos!$C$46/360 -> 787.802
...

Sheet Sensibilidad
A1: Sensibilidad del valor del patrimonio sin sinergias (millones de US$)
A3: 1. Ku (filas) × crecimiento a perpetuidad g (columnas). CPPC = Ku − t × Kd × D/V; FCF₂₀₁₃ = NOPAT₂₀₁₂(1+g)(1 − g/ROIC).
B4: 0.015 | C4: 0.02 | D4: 0.025 | E4: 0.03 | F4: 0.035 | G4: 0.04
A5: 0.075 | B5: =NPV($A5,Proyeccion!$D$28:$H$28)+Proyeccion!$H$40+Proyeccion!$H$17*(1+B$4)*(1-B$4/Proyeccion!$H$30)/(($A5-Supuestos!$C$6*Supuestos!$C$7*Costo_Capital!$C$11)-B$4)/(1+$A5)^5+Valoracion!$C$20-Valoracion!$C$26 -> 7110.6906 | C5: =NPV($A5,Proyeccion!$D$28:$H$28)+Proyeccion!$H$40+Proyeccion!$H$17*(1+C$4)*(1-C$4/Proyeccion!$H$30)/(($A5-Supuestos!$C$6*Supuestos!$C$7*Costo_Capital!$C$11)-C$4)/(1+$A5)^5+Valoracion!$C$20-Valoracion!$C$26 -> 7334.3291 | D5: =NPV($A5,Proyeccion!$D$28:$H$28)+Proyeccion!$H$40+Proyeccion!$H$17*(1+D$4)*(1-D$4/Proyeccion!$H$30)/(($A5-Supuestos!$C$6*Supuestos!$C$7*Costo_Capital!$C$11)-D$4)/(1+$A5)^5+Valoracion!$C$20-Valoracion!$C$26 -> 7605.6952 | E5: =NPV($A5,Proyeccion!$D$28:$H$28)+Proyeccion!$H$40+Proyeccion!$H$17*(1+E$4)*(1-E$4/Proyeccion!$H$30)/(($A5-Supuestos!$C$6*Supuestos!$C$7*Costo_Capital!$C$11)-E$4)/(1+$A5)^5+Valoracion!$C$20-Valoracion!$C$26 -> 7943.2338 | F5: =NPV($A5,Proyeccion!$D$28:$H$28)+Proyeccion!$H$40+Proyeccion!$H$17*(1+F$4)*(1-F$4/Proyeccion!$H$30)/(($A5-Supuestos!$C$6*Supuestos!$C$7*Costo_Capital!$C$11)-F$4)/(1+$A5)^5+Valoracion!$C$20-Valoracion!$C$26 -> 8376.2998 | G5: =NPV($A5,Proyeccion!$D$28:$H$28)+Proyeccion!$H$40+Proyeccion!$H$17*(1+G$4)*(1-G$4/Proyeccion!$H$30)/(($A5-Supuestos!$C$6*Supuestos!$C$7*Costo_Capital!$C$11)-G$4)/(1+$A5)^5+Valoracion!$C$20-Valoracion!$C$26 -> 8954.6241
A6: 0.0775 | B6: =NPV($A6,Proyeccion!$D$28:$H$28)+Proyeccion!$H$40+Proyeccion!$H$17*(1+B$4)*(1-B$4/Proyeccion!$H$30)/(($A6-Supuestos!$C$6*Supuestos!$C$7*Costo_Capital!$C$11)-B$4)/(1+$A6)^5+Valoracion!$C$20-Valoracion!$C$26 -> 6831.207 | C6: =NPV($A6,Proyeccion!$D$28:$H$28)+Proyeccion!$H$40+Proyeccion!$H$17*(1+C$4)*(1-C$4/Proyeccion!$H$30)/(($A6-Supuestos!$C$6*Supuestos!$C$7*Costo_Capital!$C$11)-C$4)/(1+$A6)^5+Valoracion!$C$20-Valoracion!$C$26 -> 7020.5929 | D6: =NPV($A6,Proyeccion!$D$28:$H$28)+Proyeccion!$H$40+Proyeccion!$H$17*(1+D$4)*(1-D$4/Proyeccion!$H$30)/(($A6-Supuestos!$C$6*Supuestos!$C$7*Costo_Capital!$C$11)-D$4)/(1+$A6)^5+Valoracion!$C$20-Valoracion!$C$26 -> 7247.7705 | E6: =NPV($A6,Proyeccion!$D$28:$H$28)+Proyeccion!$H$40+Proyeccion!$H$17*(1+E$4)*(1-E$4/Proyeccion!$H$30)/(($A6-Supuestos!$C$6*Supuestos!$C$7*Costo_Capital!$C$11)-E$4)/(1+$A6)^5+Valoracion!$C$20-Valoracion!$C$26 -> 7526.4609 | F6: =NPV($A6,Proyeccion!$D$28:$H$28)+Proyeccion!$H$40+Proyeccion!$H$17*(1+F$4)*(1-F$4/Proyeccion!$H$30)/(($A6-Supuestos!$C$6*Supuestos!$C$7*Costo_Capital!$C$11)-F$4)/(1+$A6)^5+Valoracion!$C$20-Valoracion!$C$26 -> 7877.9427 | G6: =NPV($A6,Proyeccion!$D$28:$H$28)+Proyeccion!$H$40+Proyeccion!$H$17*(1+G$4)*(1-G$4/Proyeccion!$H$30)/(($A6-Supuestos!$C$6*Supuestos!$C$7*Costo_Capital!$C$11)-G$4)/(1+$A6)^5+Valoracion!$C$20-Valoracion!$C$26 -> 8337.085
A7: 0.08 | B7: =NPV($A7,Proyeccion!$D$28:$H$28)+Proyeccion!$H$40+Proyeccion!$H$17*(1+B$4)*(1-B$4/Proyeccion!$H$30)/(($A7-Supuestos!$C$6*Supuestos!$C$7*Costo_Capital!$C$11)-B$4)/(1+$A7)^5+Valoracion!$C$20-Valoracion!$C$26 -> 6575.5605 | C7: =NPV($A7,Proyeccion!$D$28:$H$28)+Proyeccion!$H$40+Proyeccion!$H$17*(1+C$4)*(1-C$4/Proyeccion!$H$30)/(($A7-Supuestos!$C$6*Supuestos!$C$7*Costo_Capital!$C$11)-C$4)/(1+$A7)^5+Valoracion!$C$20-Valoracion!$C$26 -> 6736.0428 | D7: =NPV($A7,Proyeccion!$D$28:$H$28)+Proyeccion!$H$40+Proyeccion!$H$17*(1+D$4)*(1-D$4/Proyeccion!$H$30)/(($A7-Supuestos!$C$6*Supuestos!$C$7*Costo_Capital!$C$11)-D$4)/(1+$A7)^5+Valoracion!$C$20-Valoracion!$C$26 -> 6926.4937 | E7: =NPV($A7,Proyeccion!$D$28:$H$28)+Proyeccion!$H$40+Proyeccion!$H$17*(1+E$4)*(1-E$4/Proyeccion!$H$30)/(($A7-Supuestos!$C$6*Supuestos!$C$7*Costo_Capital!$C$11)-E$4)/(1+$A7)^5+Valoracion!$C$20-Valoracion!$C$26 -> 7157.1735 | F7: =NPV($A7,Proyeccion!$D$28:$H$28)+Proyeccion!$H$40+Proyeccion!$H$17*(1+F$4)*(1-F$4/Proyeccion!$H$30)/(($A7-Supuestos!$C$6*Supuestos!$C$7*Costo_Capital!$C$11)-F$4)/(1+$A7)^5+Valoracion!$C$20-Valoracion!$C$26 -> 7443.629 | G7: =NPV($A7,Proyeccion!$D$28:$H$28)+Proyeccion!$H$40+Proyeccion!$H$17*(1+G$4)*(1-G$4/Proyeccion!$H$30)/(($A7-Supuestos!$C$6*Supuestos!$C$7*Costo_Capital!$C$11)-G$4)/(1+$A7)^5+Valoracion!$C$20-Valoracion!$C$26 -> 7810.6032
A8: 0.0825 | B8: =NPV($A8,Proyeccion!$D$28:$H$28)+Proyeccion!$H$40+Proyeccion!$H$17*(1+B$4)*(1-B$4/Proyeccion!$H$30)/(($A8-Supuestos!$C$6*Supuestos!$C$7*Costo_Capital!$C$11)-B$4)/(1+$A8)^5+Valoracion!$C$20-Valoracion!$C$26 -> 6340.8342 | C8: =NPV($A8,Proyeccion!$D$28:$H$28)+Proyeccion!$H$40+Proyeccion!$H$17*(1+C$4)*(1-C$4/Proyeccion!$H$30)/(($A8-Supuestos!$C$6*Supuestos!$C$7*Costo_Capital!$C$11)-C$4)/(1+$A8)^5+Valoracion!$C$20-Valoracion!$C$26 -> 6476.791 | D8: =NPV($A8,Proyeccion!$D$28:$H$28)+Proyeccion!$H$40+Proyeccion!$H$17*(1+D$4)*(1-D$4/Proyeccion!$H$30)/(($A8-Supuestos!$C$6*Supuestos!$C$7*Costo_Capital!$C$11)-D$4)/(1+$A8)^5+Valoracion!$C$20-Valoracion!$C$26 -> 6636.5086 | E8: =NPV($A8,Proyeccion!$D$28:$H$28)+Proyeccion!$H$40+Proyeccion!$H$17*(1+E$4)*(1-E$4/Proyeccion!$H$30)/(($A8-Supuestos!$C$6*Supuestos!$C$7*Costo_Capital!$C$11)-E$4)/(1+$A8)^5+Valoracion!$C$20-Valoracion!$C$26 -> 6827.6828 | F8: =NPV($A8,Proyeccion!$D$28:$H$28)+Proyeccion!$H$40+Proyeccion!$H$17*(1+F$4)*(1-F$4/Proyeccion!$H$30)/(($A8-Supuestos!$C$6*Supuestos!$C$7*Costo_Capital!$C$11)-F$4)/(1+$A8)^5+Valoracion!$C$20-Valoracion!$C$26 -> 7061.7346 | G8: =NPV($A8,Proyeccion!$D$28:$H$28)+Proyeccion!$H$40+Proyeccion!$H$17*(1+G$4)*(1-G$4/Proyeccion!$H$30)/(($A8-Supuestos!$C$6*Supuestos!$C$7*Costo_Capital!$C$11)-G$4)/(1+$A8)^5+Valoracion!$C$20-Valoracion!$C$26 -> 7356.3757
A9: 0.085 | B9: =NPV($A9,Proyeccion!$D$28:$H$28)+Proyeccion!$H$40+Proyeccion!$H$17*(1+B$4)*(1-B$4/Proyeccion!$H$30)/(($A9-Supuestos!$C$6*Supuestos!$C$7*Costo_Capital!$C$11)-B$4)/(1+$A9)^5+Valoracion!$C$20-Valoracion!$C$26 -> 6124.568 | C9: =NPV($A9,Proyeccion!$D$28:$H$28)+Proyeccion!$H$40+Proyeccion!$H$17*(1+C$4)*(1-C$4/Proyeccion!$H$30)/(($A9-Supuestos!$C$6*Supuestos!$C$7*Costo_Capital!$C$11)-C$4)/(1+$A9)^5+Valoracion!$C$20-Valoracion!$C$26 -> 6239.6107 | D9: =NPV($A9,Proyeccion!$D$28:$H$28)+Proyeccion!$H$40+Proyeccion!$H$17*(1+D$4)*(1-D$4/Proyeccion!$H$30)/(($A9-Supuestos!$C$6*Supuestos!$C$7*Costo_Capital!$C$11)-D$4)/(1+$A9)^5+Valoracion!$C$20-Valoracion!$C$26 -> 6373.454 | E9: =NPV($A9,Proyeccion!$D$28:$H$28)+Proyeccion!$H$40+Proyeccion!$H$17*(1+E$4)*(1-E$4/Proyeccion!$H$30)/(($A9-Supuestos!$C$6*Supuestos!$C$7*Costo_Capital!$C$11)-E$4)/(1+$A9)^5+Valoracion!$C$20-Valoracion!$C$26 -> 6531.875 | F9: =NPV($A9,Proyeccion!$D$28:$H$28)+Proyeccion!$H$40+Proyeccion!$H$17*(1+F$4)*(1-F$4/Proyeccion!$H$30)/(($A9-Supuestos!$C$6*Supuestos!$C$7*Costo_Capital!$C$11)-F$4)/(1+$A9)^5+Valoracion!$C$20-Valoracion!$C$26 -> 6723.2882 | G9: =NPV($A9,Proyeccion!$D$28:$H$28)+Proyeccion!$H$40+Proyeccion!$H$17*(1+G$4)*(1-G$4/Proyeccion!$H$30)/(($A9-Supuestos!$C$6*Supuestos!$C$7*Costo_Capital!$C$11)-G$4)/(1+$A9)^5+Valoracion!$C$20-Valoracion!$C$26 -> 6960.444
A10: 0.0875 | B10: =NPV($A10,Proyeccion!$D$28:$H$28)+Proyeccion!$H$40+Proyeccion!$H$17*(1+B$4)*(1-B$4/Proyeccion!$H$30)/(($A10-Supuestos!$C$6*Supuestos!$C$7*Costo_Capital!$C$11)-B$4)/(1+$A10)^5+Valoracion!$C$20-Valoracion!$C$26 -> 5924.673 | C10: =NPV($A10,Proyeccion!$D$28:$H$28)+Proyeccion!$H$40+Proyeccion!$H$17*(1+C$4)*(1-C$4/Proyeccion!$H$30)/(($A10-Supuestos!$C$6*Supuestos!$C$7*Costo_Capital!$C$11)-C$4)/(1+$A10)^5+Valoracion!$C$20-Valoracion!$C$26 -> 6021.8017 | D10: =NPV($A10,Proyeccion!$D$28:$H$28)+Proyeccion!$H$40+Proyeccion!$H$17*(1+D$4)*(1-D$4/Proyeccion!$H$30)/(($A10-Supuestos!$C$6*Supuestos!$C$7*Costo_Capital!$C$11)-D$4)/(1+$A10)^5+Valoracion!$C$20-Valoracion!$C$26 -> 6133.7433 | E10: =NPV($A10,Proyeccion!$D$28:$H$28)+Proyeccion!$H$40+Proyeccion!$H$17*(1+E$4)*(1-E$4/Proyeccion!$H$30)/(($A10-Supuestos!$C$6*Supuestos!$C$7*Costo_Capital!$C$11)-E$4)/(1+$A10)^5+Valoracion!$C$20-Valoracion!$C$26 -> 6264.828 | F10: =NPV($A10,Proyeccion!$D$28:$H$28)+Proyeccion!$H$40+Proyeccion!$H$17*(1+F$4)*(1-F$4/Proyeccion!$H$30)/(($A10-Supuestos!$C$6*Supuestos!$C$7*Costo_Capital!$C$11)-F$4)/(1+$A10)^5+Valoracion!$C$20-Valoracion!$C$26 -> 6421.2557 | G10: =NPV($A10,Proyeccion!$D$28:$H$28)+Proyeccion!$H$40+Proyeccion!$H$17*(1+G$4)*(1-G$4/Proyeccion!$H$30)/(($A10-Supuestos!$C$6*Supuestos!$C$7*Costo_Capital!$C$11)-G$4)/(1+$A10)^5+Valoracion!$C$20-Valoracion!$C$26 -> 6612.228
A11: 0.09 | B11: =NPV($A11,Proyeccion!$D$28:$H$28)+Proyeccion!$H$40+Proyeccion!$H$17*(1+B$4)*(1-B$4/Proyeccion!$H$30)/(($A11-Supuestos!$C$6*Supuestos!$C$7*Costo_Capital!$C$11)-B$4)/(1+$A11)^5+Valoracion!$C$20-Valoracion!$C$26 -> 5739.3638 | C11: =NPV($A11,Proyeccion!$D$28:$H$28)+Proyeccion!$H$40+Proyeccion!$H$17*(1+C$4)*(1-C$4/Proyeccion!$H$30)/(($A11-Supuestos!$C$6*Supuestos!$C$7*Costo_Capital!$C$11)-C$4)/(1+$A11)^5+Valoracion!$C$20-Valoracion!$C$26 -> 5821.0866 | D11: =NPV($A11,Proyeccion!$D$28:$H$28)+Proyeccion!$H$40+Proyeccion!$H$17*(1+D$4)*(1-D$4/Proyeccion!$H$30)/(($A11-Supuestos!$C$6*Supuestos!$C$7*Costo_Capital!$C$11)-D$4)/(1+$A11)^5+Valoracion!$C$20-Valoracion!$C$26 -> 5914.3998 | E11: =NPV($A11,Proyeccion!$D$28:$H$28)+Proyeccion!$H$40+Proyeccion!$H$17*(1+E$4)*(1-E$4/Proyeccion!$H$30)/(($A11-Supuestos!$C$6*Supuestos!$C$7*Costo_Capital!$C$11)-E$4)/(1+$A11)^5+Valoracion!$C$20-Valoracion!$C$26 -> 6022.5341 | F11: =NPV($A11,Proyeccion!$D$28:$H$28)+Proyeccion!$H$40+Proyeccion!$H$17*(1+F$4)*(1-F$4/Proyeccion!$H$30)/(($A11-Supuestos!$C$6*Supuestos!$C$7*Costo_Capital!$C$11)-F$4)/(1+$A11)^5+Valoracion!$C$20-Valoracion!$C$26 -> 6150.0439 | G11: =NPV($A11,Proyeccion!$D$28:$H$28)+Proyeccion!$H$40+Proyeccion!$H$17*(1+G$4)*(1-G$4/Proyeccion!$H$30)/(($A11-Supuestos!$C$6*Supuestos!$C$7*Costo_Capital!$C$11)-G$4)/(1+$A11)^5+Valoracion!$C$20-Valoracion!$C$26 -> 6303.5627
A12: Base: Ku y g del modelo → | B12: =Costo_Capital!$C$10 -> 0.082337439 | C12: =Proyeccion!$H$34 -> 0.027801065 | D12: =Valoracion!$C$33 -> 6758.3437
A14: 2. Múltiplo VE/EBITDA terminal (valor terminal por múltiplo, descontado a Ku)
A15: Múltiplo | B15: 4 | C15: 5 | D15: 6 | E15: 7 | F15: 8 | G15: 9 | H15: 10 | I15: 11
A16: Patrimonio | B16: =Valoracion!$C$8+Valoracion!$C$10+Proyeccion!$H$12*B15/(1+Costo_Capital!$C$10)^5+Valoracion!$C$20-Valoracion!$C$26 -> 6714.8924 | C16: =Valoracion!$C$8+Valoracion!$C$10+Proyeccion!$H$12*C15/(1+Costo_Capital!$C$10)^5+Valoracion!$C$20-Valoracion!$C$26 -> 7844.1405 | D16: =Valoracion!$C$8+Valoracion!$C$10+Proyeccion!$H$12*D15/(1+Costo_Capital!$C$10)^5+Valoracion!$C$20-Valoracion!$C$26 -> 8973.3886 | E16: =Valoracion!$C$8+Valoracion!$C$10+Proyeccion!$H$12*E15/(1+Costo_Capital!$C$10)^5+Valoracion!$C$20-Valoracion!$C$26 -> 10102.637 | F16: =Valoracion!$C$8+Valoracion!$C$10+Proyeccion!$H$12*F15/(1+Costo_Capital!$C$10)^5+Valoracion!$C$20-Valoracion!$C$26 -> 11231.885 | G16: =Valoracion!$C$8+Valoracion!$C$10+Proyeccion!$H$12*G15/(1+Costo_Capital!$C$10)^5+Valoracion!$C$20-Valoracion!$C$26 -> 12361.133 | H16: =Valoracion!$C$8+Valoracion!$C$10+Proyeccion!$H$12*H15/(1+Costo_Capital!$C$10)^5+Valoracion!$C$20-Valoracion!$C$26 -> 13490.381 | I16: =Valoracion!$C$8+Valoracion!$C$10+Proyeccion!$H$12*I15/(1+Costo_Capital!$C$10)^5+Valoracion!$C$20-Valoracion!$C$26 -> 14619.629
A18: 3. Descuento por iliquidez | G18: 5. Realización de las sinergias
B19: Ninguno (base) | C19: Costo de salir a bolsa | D19: Anexo 8 (lectura) | E19: Regla práctica | F19: Académico
A20: Descuento | B20: =0 -> 0 | C20: =Supuestos!$C$16 -> 0.1 | D20: =Supuestos!$C$17 -> 0.157 | E20: =Supuestos!$C$18 -> 0.25 | F20: =Supuestos!$C$19 -> 0.35 | G20: Realizado | H20: 0 | I20: 0.5 | J20: 1
A21: Patrimonio | B21: =Valoracion!$C$33*(1-B20) -> 6758.3437 | C21: =Valoracion!$C$33*(1-C20) -> 6082.5093 | D21: =Valoracion!$C$33*(1-D20) -> 5697.2838 | E21: =Valoracion!$C$33*(1-E20) -> 5068.7578 | F21: =Valoracion!$C$33*(1-F20) -> 4392.9234 | G21: Patrimonio | H21: =Valoracion!$C$35+H20*Sinergias!$E$28 -> 6758.3437 | I21: =Valoracion!$C$35+I20*Sinergias!$E$28 -> 7860.8449 | J21: =Valoracion!$C$35+J20*Sinergias!$E$28 -> 8963.3461
A23: 4. Tornado: efecto de cada decisión sobre el patrimonio sin sinergias
B24: Bajo | C24: Alto | D24: Rango | E24: Supuesto
A25: g ± 0,5 pp | B25: =NPV(Costo_Capital!$C$10,Proyeccion!$D$28:$H$28)+Proyeccion!$H$40+Proyeccion!$H$17*(1+Proyeccion!$H$34-Supuestos!$C$32)*(1-(Proyeccion!$H$34-Supuestos!$C$32)/Proyeccion!$H$30)/((Costo_Capital!$C$16)-(Proyeccion!$H$34-Supuestos!$C$32))/(1+Costo_Capital!$C$10)^5+Valoracion!$C$20-Valoracion!$C$26 -> 6580.0463 | C25: =NPV(Costo_Capital!$C$10,Proyeccion!$D$28:$H$28)+Proyeccion!$H$40+Proyeccion!$H$17*(1+Proyeccion!$H$34+Supuestos!$C$32)*(1-(Proyeccion!$H$34+Supuestos!$C$32)/Proyeccion!$H$30)/((Costo_Capital!$C$16)-(Proyeccion!$H$34+Supuestos!$C$32))/(1+Costo_Capital!$C$10)^5+Valoracion!$C$20-Valoracion!$C$26 -> 6974.5318 | D25: =ABS(C25-B25) -> 394.48546 | E25: g del modelo ± 0,5 pp
A26: Método de beta (opciones 1 a 3) | B26: =MIN(Costo_Capital!$F$24:$F$26) -> 6747.8895 | C26: =MAX(Costo_Capital!$F$24:$F$26) -> 7208.3436 | D26: =ABS(C26-B26) -> 460.45407 | E26: Hamada / Harris-Pringle
A27: PRM 4% - 6% | B27: =MIN(Costo_Capital!$F$27:$F$28) -> 6008.3836 | C27: =MAX(Costo_Capital!$F$27:$F$28) -> 7773.0706 | D27: =ABS(C27-B27) -> 1764.6871 | E27: Supuesto propio
A28: D/V objetivo (mediana a 50%) | B28: =MIN(Costo_Capital!$F$29:$F$31) -> 6758.3437 | C28: =MAX(Costo_Capital!$F$29:$F$31) -> 7262.5416 | D28: =ABS(C28-B28) -> 504.19791 | E28: Anexo 7 y R&R
A29: Valor terminal: perpetuidad vs. múltiplo | B29: =MIN(Valoracion!$C$33,Valoracion!$C$46) -> 6758.3437 | C29: =MAX(Valoracion!$C$33,Valoracion!$C$46) -> 13866.909 | D29: =ABS(C29-B29) -> 7108.5657 | E29: Anexo 7
A30: Afiliadas y minoritario: libros vs. P/U | B30: =Valoracion!$C$33-Valoracion!$C$17+Historicos!$E$47+Valoracion!$C$24-Historicos!$E$68 -> 5440.9549 | C30: =Valoracion!$C$33 -> 6758.3437 | D30: =ABS(C30-B30) -> 1317.3888 | E30: Nota 3
A31: Descuento por iliquidez 0% - 25% | B31: =Valoracion!$C$33*(1-Supuestos!$C$18) -> 5068.7578 | C31: =Valoracion!$C$33 -> 6758.3437 | D31: =ABS(C31-B31) -> 1689.5859 | E31: Caso, p. 8
A32: Escenario combinado de riesgo | B32: =Escenarios!$F$186 -> 4640.8903 | C32: =Valoracion!$C$33 -> 6758.3437 | D32: =ABS(C32-B32) -> 2117.4534 | E32: Hoja Escenarios
A34: Variable con mayor rango | B34: =INDEX(A25:A32,MATCH(MAX(D25:D32),D25:D32,0)) -> Valor terminal: perpetuidad vs. múltiplo

Sheet Verificacion
A1: Verificación cruzada: Python independiente vs. Excel
A3: Cifra | B3: Excel | C3: Python | D3: Diferencia | E3: ¿Coincide?
A4: rf (Supuestos!C9) | B4: =Supuestos!C9 -> 0.0425 | C4: 0.0425 | D4: =ABS(B4-C4) -> 0 | E4: =IF(D4<0.0001,"Sí","NO") -> Sí
A5: beta_u_hamada (Comparables!C28) | B5: =Comparables!C28 -> 0.81554448 | C5: 0.81554448 | D5: =ABS(B5-C5) -> 0 | E5: =IF(D5<0.0001,"Sí","NO") -> Sí
A6: beta_u_hp0 (Comparables!D28) | B6: =Comparables!D28 -> 0.72644579 | C6: 0.72644579 | D6: =ABS(B6-C6) -> 0 | E6: =IF(D6<0.0001,"Sí","NO") -> Sí
A7: beta_u (Costo_Capital!C9) | B7: =Costo_Capital!C9 -> 0.79674879 | C7: 0.79674879 | D7: =ABS(B7-C7) -> 0 | E7: =IF(D7<0.0001,"Sí","NO") -> Sí
A8: ku (Costo_Capital!C10) | B8: =Costo_Capital!C10 -> 0.082337439 | C8: 0.082337439 | D8: =ABS(B8-C8) -> 0 | E8: =IF(D8<0.0001,"Sí","NO") -> Sí
A9: wacc (Costo_Capital!C17) | B9: =Costo_Capital!C17 -> 0.076150776 | C9: 0.076150776 | D9: =ABS(B9-C9) -> 0 | E9: =IF(D9<0.0001,"Sí","NO") -> Sí
A10: wacc_formula_completa (Costo_Capital!C16) | B10: =Costo_Capital!C16 -> 0.076150776 | C10: 0.076150776 | D10: =ABS(B10-C10) -> 0 | E10: =IF(D10<0.0001,"Sí","NO") -> Sí
A11: d0 (Deuda!C5) | B11: =Deuda!C5 -> 3757.5455 | C11: 3757.5455 | D11: =ABS(B11-C11) -> 0 | E11: =IF(D11<0.0001,"Sí","NO") -> Sí
A12: cuota (Deuda!C6) | B12: =Deuda!C6 -> 40.779242 | C12: 40.779242 | D12: =ABS(B12-C12) -> 3.126388e-13 | E12: =IF(D12<0.0001,"Sí","NO") -> Sí
A13: int_2008 (Deuda!L9) | B13: =Deuda!L9 -> 199.42896 | C13: 199.42896 | D13: =ABS(B13-C13) -> 0 | E13: =IF(D13<0.0001,"Sí","NO") -> Sí
A14: bullet (Deuda!P11) | B14: =Deuda!P11 -> 2134.909 | C14: 2134.909 | D14: =ABS(B14-C14) -> 2.0008883e-11 | E14: =IF(D14<0.0001,"Sí","NO") -> Sí
A15: pv_ts (Valoracion!C10) | B15: =Valoracion!C10 -> 284.78312 | C15: 284.78312 | D15: =ABS(B15-C15) -> 0 | E15: =IF(D15<0.0001,"Sí","NO") -> Sí
A16: rev_2012 (Proyeccion!H8) | B16: =Proyeccion!H8 -> 6806.5027 | C16: 6806.5027 | D16: =ABS(B16-C16) -> 0 | E16: =IF(D16<0.0001,"Sí","NO") -> Sí
A17: ebitda_2012 (Proyeccion!H12) | B17: =Proyeccion!H12 -> 1677.2692 | C17: 1677.2692 | D17: =ABS(B17-C17) -> 0 | E17: =IF(D17<0.0001,"Sí","NO") -> Sí
A18: fcf_2008 (Proyeccion!D28) | B18: =Proyeccion!D28 -> 291.62324 | C18: 291.62324 | D18: =ABS(B18-C18) -> 0 | E18: =IF(D18<0.0001,"Sí","NO") -> Sí
A19: fcf_2012 (Proyeccion!H28) | B19: =Proyeccion!H28 -> 318.6437 | C19: 318.6437 | D19: =ABS(B19-C19) -> 0 | E19: =IF(D19<0.0001,"Sí","NO") -> Sí
A20: roic_2012 (Proyeccion!H30) | B20: =Proyeccion!H30 -> 0.1041873 | C20: 0.1041873 | D20: =ABS(B20-C20) -> 0 | E20: =IF(D20<0.0001,"Sí","NO") -> Sí
A21: g (Valoracion!C7) | B21: =Valoracion!C7 -> 0.027801065 | C21: 0.027801065 | D21: =ABS(B21-C21) -> 0 | E21: =IF(D21<0.0001,"Sí","NO") -> Sí
A22: tv (Proyeccion!H36) | B22: =Proyeccion!H36 -> 6773.615 | C22: 6773.615 | D22: =ABS(B22-C22) -> 0 | E22: =IF(D22<0.0001,"Sí","NO") -> Sí
A23: pv_fcf (Valoracion!C8) | B23: =Valoracion!C8 -> 1258.417 | C23: 1258.417 | D23: =ABS(B23-C23) -> 4.7748472e-12 | E23: =IF(D23<0.0001,"Sí","NO") -> Sí
A24: v_ops (Valoracion!C11) | B24: =Valoracion!C11 -> 6103.6439 | C24: 6103.6439 | D24: =ABS(B24-C24) -> 0 | E24: =IF(D24<0.0001,"Sí","NO") -> Sí
A25: nooper (Valoracion!C20) | B25: =Valoracion!C20 -> 1944.4871 | C25: 1944.4871 | D25: =ABS(B25-C25) -> 0 | E25: =IF(D25<0.0001,"Sí","NO") -> Sí
A26: claims (Valoracion!C26) | B26: =Valoracion!C26 -> 1289.7873 | C26: 1289.7873 | D26: =ABS(B26-C26) -> 0 | E26: =IF(D26<0.0001,"Sí","NO") -> Sí
A27: equity (Valoracion!C33) | B27: =Valoracion!C33 -> 6758.3437 | C27: 6758.3437 | D27: =ABS(B27-C27) -> 0 | E27: =IF(D27<0.0001,"Sí","NO") -> Sí
A28: sin_bh (Valoracion!C36) | B28: =Valoracion!C36 -> 651.15411 | C28: 651.15411 | D28: =ABS(B28-C28) -> 0 | E28: =IF(D28<0.0001,"Sí","NO") -> Sí
A29: sin_rev (Valoracion!C37) | B29: =Valoracion!C37 -> 1553.8483 | C29: 1553.8483 | D29: =ABS(B29-C29) -> 0 | E29: =IF(D29<0.0001,"Sí","NO") -> Sí
A30: eq_sin (Valoracion!C38) | B30: =Valoracion!C38 -> 8963.3461 | C30: 8963.3461 | D30: =ABS(B30-C30) -> 0 | E30: =IF(D30<0.0001,"Sí","NO") -> Sí
A31: mult_med (Comparables!P13) | B31: =Comparables!P13 -> 10.333433 | C31: 10.333433 | D31: =ABS(B31-C31) -> 0 | E31: =IF(D31<0.0001,"Sí","NO") -> Sí
A32: eq_mult (Valoracion!C46) | B32: =Valoracion!C46 -> 13866.909 | C32: 13866.909 | D32: =ABS(B32-C32) -> 0 | E32: =IF(D32<0.0001,"Sí","NO") -> Sí
A33: g_impl (Valoracion!C47) | B33: =Valoracion!C47 -> 0.066469351 | C33: 0.066469351 | D33: =ABS(B33-C33) -> 0 | E33: =IF(D33<0.0001,"Sí","NO") -> Sí
A34: eq_comb (Escenarios!F186) | B34: =Escenarios!F186 -> 4640.8903 | C34: 4640.8903 | D34: =ABS(B34-C34) -> 0 | E34: =IF(D34<0.0001,"Sí","NO") -> Sí
A35: revolver_2012 (Proyeccion!H70) | B35: =Proyeccion!H70 -> 563.43349 | C35: 563.43349 | D35: =ABS(B35-C35) -> 2.4670044e-11 | E35: =IF(D35<0.0001,"Sí","NO") -> Sí
A36: eq_wacc (Valoracion!C49) | B36: =Valoracion!C49 -> 6627.0547 | C36: 6627.0547 | D36: =ABS(B36-C36) -> 0 | E36: =IF(D36<0.0001,"Sí","NO") -> Sí
A37: dv0_ops (Valoracion!C55) | B37: =Valoracion!C55 -> 0.61562331 | C37: 0.61562331 | D37: =ABS(B37-C37) -> 0 | E37: =IF(D37<0.0001,"Sí","NO") -> Sí
A39: Valores de la columna C: calculados con verificacion/verificar.py (implementación independiente en Python).
A40: Todas coinciden (diferencia máxima en la columna D) | D40: =MAX(D4:D37) -> 2.4670044e-11 | E40: =IF(COUNTIF(E4:E37,"Sí")=34,"Sí","NO") -> Sí

Sheet Control
A1: Tabla de control: cifra del informe → celda del Excel
A3: Clave | B3: Descripción | C3: Celda | D3: Valor | F3: Controles de consistencia
A4: C001 | B4: Precio máximo (retiro): valor independiente + 100% backhaul (sin pagar sinergias de ingresos) | C4: Valoracion!C60 | D4: =Valoracion!C60 -> 7409.4978 | F4: Subtotales del estado de resultados vs. publicados | G4: =Historicos!$G$31 -> 0.049 | H4: =IF(ABS(G4)<=0.06,"OK","REVISAR") -> OK
A5: C002 | B5: Apertura: valor independiente con el descuento por iliquidez de una salida a bolsa (10%, nota 6) | C5: Valoracion!C58 | D5: =Valoracion!C58 -> 6082.5093 | F5: Balance histórico cuadra | G5: =Historicos!$G$79 -> 0 | H5: =IF(ABS(G5)<=0.001,"OK","REVISAR") -> OK
A6: C003 | B6: Objetivo: valor independiente + 50% de las sinergias de backhaul | C6: Valoracion!C59 | D6: =Valoracion!C59 -> 7083.9208 | F6: Totales del balance vs. publicados | G6: =Historicos!$G$87 -> 0.047 | H6: =IF(ABS(G6)<=0.06,"OK","REVISAR") -> OK
A7: C004 | B7: Valor de las operaciones (APV) | C7: Valoracion!C11 | D7: =Valoracion!C11 -> 6103.6439 | F7: Flujo histórico concilia con Δ caja | G7: =Historicos!$G$190 -> 3.8369308e-13 | H7: =IF(ABS(G7)<=0.001,"OK","REVISAR") -> OK
A8: C005 | B8: Total activos no operativos | C8: Valoracion!C20 | D8: =Valoracion!C20 -> 1944.4871 | F8: Tabla 3 vs. recalculado | G8: =Comparables!$O$15 -> 0.0004555402 | H8: =IF(ABS(G8)<=0.0006,"OK","REVISAR") -> OK
A9: C006 | B9: Total deuda e interés minoritario | C9: Valoracion!C26 | D9: =Valoracion!C26 -> 1289.7873 | F9: D/V publicado vs. calculado | G9: =Comparables!$O$16 -> 0 | H9: =IF(ABS(G9)<=0.0001,"OK","REVISAR") -> OK
A10: C007 | B10: Valor del patrimonio, 100%, sin sinergias (valor intrínseco independiente) | C10: Valoracion!C33 | D10: =Valoracion!C33 -> 6758.3437 | F10: Costo de clientes nuevos (Anexo 3) | G10: =Historicos!$G$145 -> 0 | H10: =IF(ABS(G10)<=0.5,"OK","REVISAR") -> OK
A11: C008 | B11: + VP sinergias de backhaul | C11: Valoracion!C36 | D11: =Valoracion!C36 -> 651.15411 | F11: ROE de la Tabla 2 | G11: =Historicos!$G$148 -> 0.00047266529 | H11: =IF(ABS(G11)<=0.0006,"OK","REVISAR") -> OK
A12: C009 | B12: + VP sinergias de ingresos empresariales | C12: Valoracion!C37 | D12: =Valoracion!C37 -> 1553.8483 | F12: Saldos de deuda vs. Anexo 6 | G12: =Deuda!$Q$15 -> 0.37649403 | H12: =IF(ABS(G12)<=0.6,"OK","REVISAR") -> OK
A13: C010 | B13: Valor del patrimonio con todas las sinergias | C13: Valoracion!C38 | D13: =Valoracion!C38 -> 8963.3461 | F13: Balance proforma cuadra | G13: =Proyeccion!$I$76 -> 0 | H13: =IF(ABS(G13)<=0.001,"OK","REVISAR") -> OK
A14: C011 | B14: VE/EBITDA 2007 implícito en el valor de las operaciones | C14: Valoracion!C51 | D14: =Valoracion!C51 -> 5.9067998 | F14: Flujo proforma concilia | G14: =Proyeccion!$I$83 -> 0 | H14: =IF(ABS(G14)<=0.001,"OK","REVISAR") -> OK
A15: C012 | B15: Costo de capital no apalancado Ku = rf + βu × PRM | C15: Costo_Capital!C10 | D15: =Costo_Capital!C10 -> 0.082337439 | F15: Bloque de valoración = Valoracion | G15: =Valoracion!$C$39 -> 0 | H15: =IF(ABS(G15)<=0.001,"OK","REVISAR") -> OK
A16: C013 | B16: CPPC (WACC) objetivo = E/V × Ke + D/V × Kd × (1 − t) | C16: Costo_Capital!C16 | D16: =Costo_Capital!C16 -> 0.076150776 | F16: Escenario base = Valoracion | G16: =Escenarios!$C$188 -> 0 | H16: =IF(ABS(G16)<=0.001,"OK","REVISAR") -> OK
A17: C014 | B17: Crecimiento a perpetuidad (g) | C17: Valoracion!C7 | D17: =Valoracion!C7 -> 0.027801065 | F17: Sinergias: total consistente | G17: =Sinergias!$E$27 -> 0 | H17: =IF(ABS(G17)<=0.001,"OK","REVISAR") -> OK
A18: C015 | B18: Valor terminal / valor de las operaciones | C18: Valoracion!C12 | D18: =Valoracion!C12 -> 0.7471674 | F18: Todos los controles | H18: =IF(COUNTIF(H4:H17,"OK")=14,"OK","REVISAR") -> OK
A19: C016 | B19: Mediana [VE/EBITDA] | C19: Comparables!P13 | D19: =Comparables!P13 -> 10.333433
A20: C017 | B20: Patrimonio con valor terminal por múltiplo (sin sinergias) | C20: Valoracion!C46 | D20: =Valoracion!C46 -> 13866.909
A21: C018 | B21: Crecimiento implícito en el múltiplo (resuelve VT = NOPAT₂₀₁₂(1+g)(1−g/ROIC)/(CPPC−g)) | C21: Valoracion!C47 | D21: =Valoracion!C47 -> 0.066469351
A22: C019 | B22: Prima del precio máximo sobre el valor independiente | C22: Valoracion!C66 | D22: =Valoracion!C66 -> 0.09634818
A23: C020 | B23: Sinergias de ingresos / total de sinergias | C23: Valoracion!C65 | D23: =Valoracion!C65 -> 0.70469233
A24: C021 | B24: Patrimonio | C24: Sensibilidad!I21 | D24: =Sensibilidad!I21 -> 7860.8449
A25: C022 | B25: Deuda inicial = intereses máximos / Kd | C25: Deuda!C5 | D25: =Deuda!C5 -> 3757.5455
A26: C023 | B26: Deuda de adquisición / valor de las operaciones (límite 50%) | C26: Valoracion!C55 | D26: =Valoracion!C55 -> 0.61562331
A27: C024 | B27: Deuda / valor máximo admitido [Valor] | C27: Supuestos!C12 | D27: =Supuestos!C12 -> 0.5
A28: C025 | B28: Deuda de adquisición / valor total de la empresa con activos no operativos | C28: Valoracion!C56 | D28: =Valoracion!C56 -> 0.46688423
A29: C026 | B29: Línea de crédito (variable de cierre) [2012] | C29: Proyeccion!H70 | D29: =Proyeccion!H70 -> 563.43349
A30: C027 | B30: Costo de la deuda (Kd), BBB+ [Valor] | C30: Supuestos!C7 | D30: =Supuestos!C7 -> 0.055
A31: C028 | B31: Diferencial sobre el bono del Tesoro a 10 años [Valor] | C31: Supuestos!C8 | D31: =Supuestos!C8 -> 0.0125
A32: C029 | B32: Prima de riesgo de mercado (PRM) [Valor] | C32: Supuestos!C10 | D32: =Supuestos!C10 -> 0.05
A33: C030 | B33: Cobertura EBITDA / intereses para dimensionar la deuda [Valor] | C33: Supuestos!C11 | D33: =Supuestos!C11 -> 5
A34: C031 | B34: Múltiplo P/U histórico de la industria [Valor] | C34: Supuestos!C15 | D34: =Supuestos!C15 -> 19.095
A35: C032 | B35: Costo de salir a bolsa (% del patrimonio), tope razonable del descuento [Valor] | C35: Supuestos!C16 | D35: =Supuestos!C16 -> 0.1
A36: C033 | B36: Descuento por iliquidez, regla práctica (20%-30%), punto medio [Valor] | C36: Supuestos!C18 | D36: =Supuestos!C18 -> 0.25
A37: C034 | B37: Descuento por iliquidez, investigación académica [Valor] | C37: Supuestos!C19 | D37: =Supuestos!C19 -> 0.35
A38: C035 | B38: Diferencia máxima de todos los subtotales del estado de resultados [Diferencia máx.] | C38: Historicos!G31 | D38: =Historicos!G31 -> 0.049
A39: C036 | B39: Control: activos − pasivos y patrimonio [Diferencia máx.] | C39: Historicos!G79 | D39: =Historicos!G79 -> 0
A40: C037 | B40: Diferencia máxima de los totales del balance [Diferencia máx.] | C40: Historicos!G87 | D40: =Historicos!G87 -> 0.047
A41: C038 | B41: Control: diferencia Tabla 3 vs. recalculado [Valor empresa (VE)] | C41: Comparables!O15 | D41: =Comparables!O15 -> 0.0004555402
A42: C039 | B42: ROE (utilidad neta / patrimonio al cierre) [2007] | C42: Historicos!E110 | D42: =Historicos!E110 -> 0.098472665
A43: C040 | B43: Control: diferencia (fila 16 − fila 14) | C43: Deuda!Q15 | D43: =Deuda!Q15 -> 0.37649403
A44: C041 | B44: Días de cartera (sobre ingresos totales) [Valor] | C44: Supuestos!C46 | D44: =Supuestos!C46 -> 41.667319
A45: C042 | B45: Días de inventario (sobre ingresos por equipos) [Valor] | C45: Supuestos!C47 | D45: =Supuestos!C47 -> 154.36021
A46: C043 | B46: Ingresos por equipos / ingresos por servicios [Valor] | C46: Supuestos!C45 | D46: =Supuestos!C45 -> 0.075047299
A47: C044 | B47: Diferencia = dividendos u otros cargos implícitos [2006] | C47: Historicos!D93 | D47: =Historicos!D93 -> 0
A48: C045 | B48: Diferencia = dividendos u otros cargos implícitos [2007] | C48: Historicos!E93 | D48: =Historicos!E93 -> -40.19
A49: C046 | B49: Variación de utilidades retenidas publicadas − utilidad neta [2006] | C49: Historicos!D94 | D49: =Historicos!D94 -> 68.886
A50: C047 | B50: Variación de utilidades retenidas publicadas − utilidad neta [2007] | C50: Historicos!E94 | D50: =Historicos!E94 -> -137.07
A51: C048 | B51: Días de ingresos diferidos (sobre ingresos por servicios) [Valor] | C51: Supuestos!C50 | D51: =Supuestos!C50 -> 14.012137
A52: C049 | B52: Gastos prepagados / costos operativos en efectivo [Valor] | C52: Supuestos!C48 | D52: =Supuestos!C48 -> 0.013806751
A53: C050 | B53: Activos operativos netos implícitos en la Tabla 2 (ingresos / rotación) [2007] | C53: Historicos!E150 | D53: =Historicos!E150 -> 3816.5029
A54: C051 | B54: Activo fijo neto (PP&E + licencias + listas de clientes) [2007] | C54: Historicos!E96 | D54: =Historicos!E96 -> 4092.917
A55: C052 | B55: Promedio [D/P publicado] | C55: Comparables!E11 | D55: =Comparables!E11 -> 0.4008595
A56: C053 | B56: Promedio [D/V publicado] | C56: Comparables!D11 | D56: =Comparables!D11 -> 0.28121199
A57: C054 | B57: Inconsistencia: D/P promedio publicado vs. D/P implícito en el D/V promedio [D/V publicado] | C57: Comparables!D17 | D57: =Comparables!D17 -> 0.39123078
A58: C055 | B58: Agile Connections [VE/EBITDA] | C58: Comparables!P7 | D58: =Comparables!P7 -> 2.6385799
A59: C056 | B59: Neuberger Wireless [VE/EBITDA] | C59: Comparables!P6 | D59: =Comparables!P6 -> 19.066686
A60: C057 | B60: EBIT (utilidad operativa) [2007] | C60: Historicos!E13 | D60: =Historicos!E13 -> 451.056
A61: C058 | B61: Capex implícito = Δ activo fijo neto + D&A [2006] | C61: Historicos!D97 | D61: =Historicos!D97 -> 741.955
A62: C059 | B62: Capex implícito = Δ activo fijo neto + D&A [2007] | C62: Historicos!E97 | D62: =Historicos!E97 -> 525.815
A63: C060 | B63: Descuento por iliquidez, Anexo 8 (empresa rentable, ingresos US$1.000 MM) [Valor] | C63: Supuestos!C17 | D63: =Supuestos!C17 -> 0.157
A64: C061 | B64: Ingresos totales [2007] | C64: Historicos!E7 | D64: =Historicos!E7 -> 3946.264
A65: C062 | B65: Crecimiento de ingresos totales [2006] | C65: Historicos!D102 | D65: =Historicos!D102 -> 0.14596645
A66: C063 | B66: Crecimiento de ingresos totales [2007] | C66: Historicos!E102 | D66: =Historicos!E102 -> 0.1362188
A67: C064 | B67: Variación de los minutos por cliente [2007] | C67: Historicos!E143 | D67: =Historicos!E143 -> 0.22017045
A68: C065 | B68: Margen EBITDA [2005] | C68: Historicos!C104 | D68: =Historicos!C104 -> 0.22998286
A69: C066 | B69: Margen EBITDA [2006] | C69: Historicos!D104 | D69: =Historicos!D104 -> 0.2490554
A70: C067 | B70: Margen EBITDA [2007] | C70: Historicos!E104 | D70: =Historicos!E104 -> 0.26184893
A71: C068 | B71: Margen EBITDA [Comparables] | C71: Historicos!G104 | D71: =Historicos!G104 -> 0.316
A72: C069 | B72: Margen EBIT [2005] | C72: Historicos!C105 | D72: =Historicos!C105 -> 0.068276821
A73: C070 | B73: Margen EBIT [2006] | C73: Historicos!D105 | D73: =Historicos!D105 -> 0.089107166
A74: C071 | B74: Margen EBIT [2007] | C74: Historicos!E105 | D74: =Historicos!E105 -> 0.1142995
A75: C072 | B75: Margen EBIT [Comparables] | C75: Historicos!G105 | D75: =Historicos!G105 -> 0.156
A76: C073 | B76: D&A / ingresos totales [2007] | C76: Historicos!E130 | D76: =Historicos!E130 -> 0.14754943
A77: C074 | B77: Margen neto [2005] | C77: Historicos!C106 | D77: =Historicos!C106 -> 0.051126036
A78: C075 | B78: Margen neto [2006] | C78: Historicos!D106 | D78: =Historicos!D106 -> 0.051679237
A79: C076 | B79: Margen neto [2007] | C79: Historicos!E106 | D79: =Historicos!E106 -> 0.079754928
A80: C077 | B80: Margen neto [Comparables] | C80: Historicos!G106 | D80: =Historicos!G106 -> 0.066
A81: C078 | B81: ROA (utilidad neta / activos totales) [2005] | C81: Historicos!C109 | D81: =Historicos!C109 -> 0.028608629
A82: C079 | B82: ROA (utilidad neta / activos totales) [2006] | C82: Historicos!D109 | D82: =Historicos!D109 -> 0.031596925
A83: C080 | B83: ROA (utilidad neta / activos totales) [2007] | C83: Historicos!E109 | D83: =Historicos!E109 -> 0.056083583
A84: C081 | B84: ROE (utilidad neta / patrimonio al cierre) [2005] | C84: Historicos!C110 | D84: =Historicos!C110 -> 0.056530044
A85: C082 | B85: ROE (utilidad neta / patrimonio al cierre) [2006] | C85: Historicos!D110 | D85: =Historicos!D110 -> 0.05996434
A86: C083 | B86: Costo del patrimonio Ke = rf + βe × PRM | C86: Costo_Capital!C15 | D86: =Costo_Capital!C15 -> 0.093032687
A87: C084 | B87: ROIC (EBIT × (1 − t) / (patrimonio + deuda), definición de la nota 7) [2005] | C87: Historicos!C111 | D87: =Historicos!C111 -> 0.032020907
A88: C085 | B88: ROIC (EBIT × (1 − t) / (patrimonio + deuda), definición de la nota 7) [2006] | C88: Historicos!D111 | D88: =Historicos!D111 -> 0.046075524
A89: C086 | B89: ROIC (EBIT × (1 − t) / (patrimonio + deuda), definición de la nota 7) [2007] | C89: Historicos!E111 | D89: =Historicos!E111 -> 0.064460376
A90: C087 | B90: Días de cartera (sobre ingresos totales, 360 días) [2005] | C90: Historicos!C112 | D90: =Historicos!C112 -> 43.041687
A91: C088 | B91: Días de cartera (sobre ingresos totales, 360 días) [2006] | C91: Historicos!D112 | D91: =Historicos!D112 -> 42.231827
A92: C089 | B92: Días de cartera (sobre ingresos totales, 360 días) [2007] | C92: Historicos!E112 | D92: =Historicos!E112 -> 39.728442
A93: C090 | B93: Días de inventario (sobre costo de equipos) [2005] | C93: Historicos!C114 | D93: =Historicos!C114 -> 65.221208
A94: C091 | B94: Días de inventario (sobre costo de equipos) [2006] | C94: Historicos!D114 | D94: =Historicos!D114 -> 74.156825
A95: C092 | B95: Días de inventario (sobre costo de equipos) [2007] | C95: Historicos!E114 | D95: =Historicos!E114 -> 56.786911
A96: C093 | B96: Días de proveedores (sobre costos operativos en efectivo) [2005] | C96: Historicos!C117 | D96: =Historicos!C117 -> 39.19962
A97: C094 | B97: Días de proveedores (sobre costos operativos en efectivo) [2006] | C97: Historicos!D117 | D97: =Historicos!D117 -> 35.179597
A98: C095 | B98: Días de proveedores (sobre costos operativos en efectivo) [2007] | C98: Historicos!E117 | D98: =Historicos!E117 -> 32.230253
A99: C096 | B99: Ciclo de caja = cartera + inventario (costo) − proveedores [2005] | C99: Historicos!C120 | D99: =Historicos!C120 -> 69.063276
A100: C097 | B100: Ciclo de caja = cartera + inventario (costo) − proveedores [2006] | C100: Historicos!D120 | D100: =Historicos!D120 -> 81.209054
A101: C098 | B101: Ciclo de caja = cartera + inventario (costo) − proveedores [2007] | C101: Historicos!E120 | D101: =Historicos!E120 -> 64.2851
...
